Workbook

Sheet Picks for Licensing Outreach
A1: Priority Band | B1: Priority Order | C1: Series Name | D1: Author Name | E1: Approx Length (Hrs) | F1: # of Books in Series | G1: First Book Name | H1: Last Book Name | I1: First Book Rating (Stars) | J1: First Book GR Ratings (#) | K1: Rating Categorisation | L1: 20-40H Avg Retention | M1: Retention Quality | N1: Sub Genre | O1: Series Type | P1: Series Era | Q1: KU 100 Category | R1: KU Feb 2026 | S1: KU April 2026 | T1: Amazon Best Rank | U1: Trope | V1: Commercial Tier | W1: MG Range | X1: Rev Share (%) | Y1: Rev Share Range | Z1: Outreach Status | AA1: Publisher / Author Name | AB1: Self Pub Flag | AC1: Author Email ID | AD1: Email Verified | AE1: Agency Email ID | AF1: Agent Name | AG1: Author Website | AH1: Contact Description | AI1: Email Status | AJ1: Outreach date | AK1: Response Status | AL1: Response Date | AM1: Status | AN1: Warm Lead? | AO1: Boilerplate Sent? | AP1: Data Quality Flag | AQ1: Draft Email | AR1: Found Email | AS1: Email Type | AT1: Email Source URL | AU1: Email Confidence | AV1: Research Notes
A2: P5 | B2: 48 | C2: Yes, Daddy | D2: Lena Little | E2: 160.92 | F2: 50 | G2: Daddy Next Door | H2: Navy Daddy | I2: 3.87 | J2: 396 | K2: Tier 3 (<5k) | L2: 1.2576 | M2: STRONG >=50% | N2: Ice Hockey / Sports Romance | O2: Long Series | P2: After 2020 | U2: Needgap | V2: 9 | W2: Up to $1,000 | X2: 12% | Y2: 12% - 18% | Z2: READY (low ratings) | AA2: Lena Little Publishing | AB2: Self-Pub | AC2: inquiry@lenalittle.com | AD2: TRUE | AG2: https://www.lenalittle.com | AH2: Email: inquiry@lenalittle.com | Website: https://www.lenalittle.com | AI2: =vlookup(C2,'Mail Merge'!B:J,9,0) | AJ2: 46207 | AP2: GREEN | AQ2: Dear Lena, I'm reaching out from Pocket FM regarding the Yes, Daddy series. We believe this series has strong potential for adaptation into serialized audio, a rapidly growing format structurally distinct from traditional audiobooks. We'd like to propose a partnership that includes a License Fee of $1,000 and 12% share of Revenue, details on the full offer are below. We understand many authors have granted exclusive audiobook rights (often to Audible). We are not seeking audiobook rights. Instead, we license serialized audio series adaptation rights, which are closer in nature to a TV dramatization, but in audio form, than to a traditional narrated audiobook. Rather than recording the manuscript verbatim, we create a scripted, episodic adaptation featuring dual-cast or full-cast performances, cinematic sound design, and structured cliffhanger arcs. Episodes run ~10 minutes and are released serially, with progression-based monetization. This format functions as an incremental revenue stream alongside print, ebook, KU, and audiobook sales, not in competition with them. Given the layered world-building and sustained narrative momentum in Yes, Daddy, we see strong alignment with this dramatized serialized format. Pocket FM is the world's largest dedicated audio series platform, trusted by leading publishers and IP holders including Naver, Kakao, Blackstone, Recorded Books, Aethon, and China Literature. Our catalog includes globally recognized titles such as Solo Leveling, The Primal Hunter, and Omniscient Reader's Viewpoint. In the past 12 months, we've delivered: 120 billion minutes of listening 18 million monthly active users $342M in revenue 200+ million global downloads Our app is rated 4.7 on the App Store and 4.5 on Google Play. Several titles have scaled meaningfully through this model, including: My Vampire System: 1B+ listens, $100M+ revenue Saving Nora: $42M revenue The Duke's Masked Bride: 641M plays The Alpha's Bride: 415M plays You can hear an example of our production quality here: https://pocketfm.com/show/ba2d9038fc3853c464c8be7a34a0576f26145106 We are proposing: License Fee: $1,000 Revenue Share: 12% of Revenue Exclusive serialized audio series adaptation rights (distinct from audiobook rights) English language (U.S./U.K.) 5-10 year term Full IP ownership retained by the author We are focused on long-term partnerships and would welcome discussion around additional titles within your catalog as well. If of interest, I'd be glad to schedule a brief call to discuss further. Best regards, Pulaksh Khimesara US Licensing & Commissioning Pocket FM
A3: P1 | B3: 50 | C3: Play by Play | D3: Jaci Burton | E3: 199.62 | F3: 18 | G3: The Perfect Play | H3: Shot on Gold | I3: 3.88 | J3: 41100 | K3: Tier 1 (>=20k) | L3: 0.0173 | M3: WEAK <30% | N3: Ice Hockey / Sports Romance | O3: Long Series | P3: Before 2020 | U3: Needgap | V3: 1 | W3: 12000 | X3: 15% | Y3: 15% - 22% | Z3: READY | AA3: Berkley | AB3: Big Pub | AC3: jaci@jaciburton.com | AD3: TRUE | AE3: kwhalen@thewhalenagency.com | AF3: Kimberly A. Whalen | AG3: http://www.jaciburton.com/ | AH3: Email: jaci@jaciburton.com | Agent: For literary | Website: http://www.jaciburton.com/ | AI3: sent to jaci and kimberly whalen | AJ3: 46207 | AP3: GREEN | AQ3: Dear Jaci, I'm reaching out from Pocket FM regarding the Play by Play series. We believe this series has strong potential for adaptation into serialized audio, a rapidly growing format structurally distinct from traditional audiobooks. We'd like to propose a partnership that includes a License Fee of $25,000 and 15% share of Revenue, details on the full offer are below. We understand many authors have granted exclusive audiobook rights (often to Audible). We are not seeking audiobook rights. Instead, we license serialized audio series adaptation rights, which are closer in nature to a TV dramatization, but in audio form, than to a traditional narrated audiobook. Rather than recording the manuscript verbatim, we create a scripted, episodic adaptation featuring dual-cast or full-cast performances, cinematic sound design, and structured cliffhanger arcs. Episodes run ~10 minutes and are released serially, with progression-based monetization. This format functions as an incremental revenue stream alongside print, ebook, KU, and audiobook sales, not in competition with them. Given the layered world-building and sustained narrative momentum in Play by Play, we see strong alignment with this dramatized serialized format. Pocket FM is the world's largest dedicated audio series platform, trusted by leading publishers and IP holders including Naver, Kakao, Blackstone, Recorded Books, Aethon, and China Literature. Our catalog includes globally recognized titles such as Solo Leveling, The Primal Hunter, and Omniscient Reader's Viewpoint. In the past 12 months, we've delivered: 120 billion minutes of listening 18 million monthly active users $342M in revenue 200+ million global downloads Our app is rated 4.7 on the App Store and 4.5 on Google Play. Several titles have scaled meaningfully through this model, including: My Vampire System: 1B+ listens, $100M+ revenue Saving Nora: $42M revenue The Duke's Masked Bride: 641M plays The Alpha's Bride: 415M plays You can hear an example of our production quality here: https://pocketfm.com/show/ba2d9038fc3853c464c8be7a34a0576f26145106 We are proposing: License Fee: $25,000 Revenue Share: 15% of Revenue Exclusive serialized audio series adaptation rights (distinct from audiobook rights) English language (U.S./U.K.) 5-10 year term Full IP ownership retained by the author We are focused on long-term partnerships and would welcome discussion around additional titles within your catalog as well. If of interest, I'd be glad to schedule a brief call to discuss further. Best regards, Pulaksh Khimesara US Licensing & Commissioning Pocket FM
A4: P0 | B4: 85 | C4: With Me in Seattle | D4: Kristen Proby | E4: 498.54 | F4: 21 | G4: Come Away with Me | H4: Imagine With Me | I4: 3.91 | J4: 63385 | K4: Tier 1 (>=20k) | L4: 0.0302 | M4: WEAK <30% | N4: Ice Hockey / Sports Romance | O4: Long Series | P4: Before 2020 | S4: Sports Romance (Paid) #30 | T4: 30 | U4: Needgap | V4: 1 | W4: 15000 | X4: 15% | Y4: 15% - 22% | Z4: NEED CONTACT | AA4: Kristen Proby | AB4: Indie | AD4: FALSE | AE4: oscar@oscarjansonsmith.com | AF4: Oscar Janson-Smith | AG4: https://www.kristenproby.com/ | AH4: Agent: Oscar Janson-Smith | Website: https://www.kristenproby.com/ | AI4: sent | AJ4: 46207 | AP4: YELLOW
A5: P0 | B5: 80 | C5: Windy City | D5: Liz Tomforde | E5: 65.85 | F5: 5 | G5: Mile High | H5: Rewind It Back | I5: 4.02 | J5: 536591 | K5: Tier 1 (>=20k) | M5: DATA_SCALE_MISMATCH | N5: Ice Hockey / Sports Romance | O5: Series | P5: Before 2020 | Q5: Sports T100 | R5: Sports T100 | S5: Sports Romance (Paid) #1 | T5: 1 | U5: Needgap | V5: 2 | W5: 20000 | X5: 15% | Y5: 15% - 22% | Z5: READY | AA5: Bloom Books | AB5: Indie | AC5: liztomforde.office@gmail.com | AD5: TRUE | AE5: andrea@dijkstraagency.com | AF5: that Liz | AG5: https://www.liztomforde.com | AH5: Email: liztomforde.office@gmail.com | Agent email: andrea@dijkstraagency.com | Agent: that Liz | Website: https://www.liztomforde.com | AI5: sent to liz and andrea | AJ5: 46207 | AP5: YELLOW | AQ5: Dear Liz, I'm reaching out from Pocket FM regarding the Windy City series. We believe this series has strong potential for adaptation into serialized audio, a rapidly growing format structurally distinct from traditional audiobooks. We'd like to propose a partnership that includes a License Fee of $20,000 and 15% share of Revenue, details on the full offer are below. We understand many authors have granted exclusive audiobook rights (often to Audible). We are not seeking audiobook rights. Instead, we license serialized audio series adaptation rights, which are closer in nature to a TV dramatization, but in audio form, than to a traditional narrated audiobook. Rather than recording the manuscript verbatim, we create a scripted, episodic adaptation featuring dual-cast or full-cast performances, cinematic sound design, and structured cliffhanger arcs. Episodes run ~10 minutes and are released serially, with progression-based monetization. This format functions as an incremental revenue stream alongside print, ebook, KU, and audiobook sales, not in competition with them. Given the layered world-building and sustained narrative momentum in Windy City, we see strong alignment with this dramatized serialized format. Pocket FM is the world's largest dedicated audio series platform, trusted by leading publishers and IP holders including Naver, Kakao, Blackstone, Recorded Books, Aethon, and China Literature. Our catalog includes globally recognized titles such as Solo Leveling, The Primal Hunter, and Omniscient Reader's Viewpoint. In the past 12 months, we've delivered: 120 billion minutes of listening 18 million monthly active users $342M in revenue 200+ million global downloads Our app is rated 4.7 on the App Store and 4.5 on Google Play. Several titles have scaled meaningfully through this model, including: My Vampire System: 1B+ listens, $100M+ revenue Saving Nora: $42M revenue The Duke's Masked Bride: 641M plays The Alpha's Bride: 415M plays You can hear an example of our production quality here: https://pocketfm.com/show/ba2d9038fc3853c464c8be7a34a0576f26145106 We are proposing: License Fee: $20,000 Revenue Share: 15% of Revenue Exclusive serialized audio series adaptation rights (distinct from audiobook rights) English language (U.S./U.K.) 5-10 year term Full IP ownership retained by the author We are focused on long-term partnerships and would welcome discussion around additional titles within your catalog as well. If of interest, I'd be glad to schedule a brief call to discuss further. Best regards, Pulaksh Khimesara US Licensing & Commissioning Pocket FM
A6: P0 | B6: 75 | C6: Leighton U | D6: C.E. Ricci | E6: 90 | F6: 5 | G6: Iced Out | H6: Fake Shot | I6: 4.1 | J6: 42272 | K6: Tier 1 (>=20k) | L6: 0.1518 | M6: WEAK <30% | N6: Ice Hockey / Sports Romance | O6: Series | P6: After 2020 | S6: Sports Romance (Paid) #9 | T6: 9 | U6: Needgap | V6: 1 | W6: 15000 | X6: 15% | Y6: 15% - 22% | Z6: NEED CONTACT | AA6: Self Pub | AB6: Self-Pub | AC6: admin@authorcericci.com | AD6: FALSE | AE6: info@twodaisy.com | AF6: Savannah Greenwell | AG6: https://www.authorcericci.com | AH6: Website: https://www.authorcericci.com | AI6: sent to 2 daily and ricci | AJ6: 46207 | AP6: YELLOW
A7: P0 | B7: 75 | C7: Puckboys | D7: Eden Finley | E7: 87.87 | F7: 10 | G7: Egotistical Puckboy | H7: Charming Puckboy | I7: 4.06 | J7: 26277 | K7: Tier 1 (>=20k) | M7: DATA_SCALE_MISMATCH | N7: Ice Hockey / Sports Romance | O7: Long Series | P7: After 2020 | Q7: Amazon Top 50 | R7: Amazon Top 50 | U7: Needgap | V7: 1 | W7: 10000 | X7: 15% | Y7: 15% - 22% | Z7: READY | AA7: Eden Finley | AB7: Self-Pub | AC7: assistant@edenfinley.com | AD7: TRUE | AF7: Contact form on official website | AG7: https://edenfinley.com/ | AH7: Email: assistant@edenfinley.com | Agent: Contact form on official website | Website: https://edenfinley.com/ | AI7: sent again | AJ7: 46207 | AP7: YELLOW | AQ7: Dear Eden, I'm reaching out from Pocket FM regarding the Puckboys series. We believe this series has strong potential for adaptation into serialized audio, a rapidly growing format structurally distinct from traditional audiobooks. We'd like to propose a partnership that includes a License Fee of $25,000 and 15% share of Revenue, details on the full offer are below. We understand many authors have granted exclusive audiobook rights (often to Audible). We are not seeking audiobook rights. Instead, we license serialized audio series adaptation rights, which are closer in nature to a TV dramatization, but in audio form, than to a traditional narrated audiobook. Rather than recording the manuscript verbatim, we create a scripted, episodic adaptation featuring dual-cast or full-cast performances, cinematic sound design, and structured cliffhanger arcs. Episodes run ~10 minutes and are released serially, with progression-based monetization. This format functions as an incremental revenue stream alongside print, ebook, KU, and audiobook sales, not in competition with them. Given the layered world-building and sustained narrative momentum in Puckboys, we see strong alignment with this dramatized serialized format. Pocket FM is the world's largest dedicated audio series platform, trusted by leading publishers and IP holders including Naver, Kakao, Blackstone, Recorded Books, Aethon, and China Literature. Our catalog includes globally recognized titles such as Solo Leveling, The Primal Hunter, and Omniscient Reader's Viewpoint. In the past 12 months, we've delivered: 120 billion minutes of listening 18 million monthly active users $342M in revenue 200+ million global downloads Our app is rated 4.7 on the App Store and 4.5 on Google Play. Several titles have scaled meaningfully through this model, including: My Vampire System: 1B+ listens, $100M+ revenue Saving Nora: $42M revenue The Duke's Masked Bride: 641M plays The Alpha's Bride: 415M plays You can hear an example of our production quality here: https://pocketfm.com/show/ba2d9038fc3853c464c8be7a34a0576f26145106 We are proposing: License Fee: $25,000 Revenue Share: 15% of Revenue Exclusive serialized audio series adaptation rights (distinct from audiobook rights) English language (U.S./U.K.) 5-10 year term Full IP ownership retained by the author We are focused on long-term partnerships and would welcome discussion around additional titles within your catalog as well. If of interest, I'd be glad to schedule a brief call to discuss further. Best regards, Pulaksh Khimesara US Licensing & Commissioning Pocket FM | AV7: NOTE: Already contacted Eden Finley for: CU Hockey
A8: P1 | C8: The Curvy Girls Club | D8: Kelsie Stelting | E8: 174.72 | F8: 14 | G8: Curvy Girls Can't Date Quarterbacks | H8: Curvy Girls Can't Date Point Guards | I8: 3.96 | J8: 16756 | K8: Tier 2 (>=5k) | M8: WEAK <30% | N8: Ice Hockey / Sports Romance | O8: Long Series | U8: Needgap | V8: 5 | W8: $12,500 - $17,500 | X8: 15% | Y8: 15% - 20% | Z8: READY | AA8: Indie | AB8: Indie | AC8: kelsie@kelsiestelting.com | AD8: TRUE | AG8: https://kelsiestelting.com/ | AH8: Email: kelsie@kelsiestelting.com | Website: https://kelsiestelting.com/ | AI8: sent- warm lead | AJ8: 25-03-2026 | AP8: GREEN | AQ8: Dear Kelsie, I'm reaching out from Pocket FM regarding the The Curvy Girls Club series. We believe this series has strong potential for adaptation into serialized audio, a rapidly growing format structurally distinct from traditional audiobooks. We'd like to propose a partnership that includes a License Fee of $17,500 and 15% share of Revenue, details on the full offer are below. We understand many authors have granted exclusive audiobook rights (often to Audible). We are not seeking audiobook rights. Instead, we license serialized audio series adaptation rights, which are closer in nature to a TV dramatization, but in audio form, than to a traditional narrated audiobook. Rather than recording the manuscript verbatim, we create a scripted, episodic adaptation featuring dual-cast or full-cast performances, cinematic sound design, and structured cliffhanger arcs. Episodes run ~10 minutes and are released serially, with progression-based monetization. This format functions as an incremental revenue stream alongside print, ebook, KU, and audiobook sales, not in competition with them. Given the layered world-building and sustained narrative momentum in The Curvy Girls Club, we see strong alignment with this dramatized serialized format. Pocket FM is the world's largest dedicated audio series platform, trusted by leading publishers and IP holders including Naver, Kakao, Blackstone, Recorded Books, Aethon, and China Literature. Our catalog includes globally recognized titles such as Solo Leveling, The Primal Hunter, and Omniscient Reader's Viewpoint. In the past 12 months, we've delivered: 120 billion minutes of listening 18 million monthly active users $342M in revenue 200+ million global downloads Our app is rated 4.7 on the App Store and 4.5 on Google Play. Several titles have scaled meaningfully through this model, including: My Vampire System: 1B+ listens, $100M+ revenue Saving Nora: $42M revenue The Duke's Masked Bride: 641M plays The Alpha's Bride: 415M plays You can hear an example of our production quality here: https://pocketfm.com/show/ba2d9038fc3853c464c8be7a34a0576f26145106 We are proposing: License Fee: $17,500 Revenue Share: 15% of Revenue Exclusive serialized audio series adaptation rights (distinct from audiobook rights) English language (U.S./U.K.) 5-10 year term Full IP ownership retained by the author We are focused on long-term partnerships and would welcome discussion around additional titles within your catalog as well. If of interest, I'd be glad to schedule a brief call to discuss further. Best regards, Pulaksh Khimesara US Licensing & Commissioning Pocket FM
A9: P1 | B9: 50 | C9: Brooklyn Bruisers | D9: Sarina Bowen | E9: 110.82 | F9: 13 | G9: Rookie Move | H9: Must Love Hockey | I9: 3.86 | J9: 17149 | K9: Tier 2 (>=5k) | L9: 0.0369 | M9: WEAK <30% | N9: Ice Hockey / Sports Romance | O9: Long Series | P9: Before 2020 | S9: Contemporary Romance (Paid) #72 | T9: 72 | U9: Needgap | V9: 5 | W9: 10000 | X9: 15% | Y9: 15% - 20% | Z9: READY | AA9: Rennie Road Books | AB9: Self-Pub | AC9: sarina.bowen@yahoo.com | AD9: TRUE | AE9: mollie.glickasst@caa.com | AF9: Mollie GLick | AG9: https://sarinabowen.com | AH9: Email: sarina.bowen@yahoo.com | Agent: in English is | Website: https://sarinabowen.com | AI9: sent to sarina and | AJ9: 46177 | AP9: GREEN | AQ9: Dear Sarina, I'm reaching out from Pocket FM regarding the Brooklyn Bruisers series. We believe this series has strong potential for adaptation into serialized audio, a rapidly growing format structurally distinct from traditional audiobooks. We'd like to propose a partnership that includes a License Fee of $17,500 and 15% share of Revenue, details on the full offer are below. We understand many authors have granted exclusive audiobook rights (often to Audible). We are not seeking audiobook rights. Instead, we license serialized audio series adaptation rights, which are closer in nature to a TV dramatization, but in audio form, than to a traditional narrated audiobook. Rather than recording the manuscript verbatim, we create a scripted, episodic adaptation featuring dual-cast or full-cast performances, cinematic sound design, and structured cliffhanger arcs. Episodes run ~10 minutes and are released serially, with progression-based monetization. This format functions as an incremental revenue stream alongside print, ebook, KU, and audiobook sales, not in competition with them. Given the layered world-building and sustained narrative momentum in Brooklyn Bruisers, we see strong alignment with this dramatized serialized format. Pocket FM is the world's largest dedicated audio series platform, trusted by leading publishers and IP holders including Naver, Kakao, Blackstone, Recorded Books, Aethon, and China Literature. Our catalog includes globally recognized titles such as Solo Leveling, The Primal Hunter, and Omniscient Reader's Viewpoint. In the past 12 months, we've delivered: 120 billion minutes of listening 18 million monthly active users $342M in revenue 200+ million global downloads Our app is rated 4.7 on the App Store and 4.5 on Google Play. Several titles have scaled meaningfully through this model, including: My Vampire System: 1B+ listens, $100M+ revenue Saving Nora: $42M revenue The Duke's Masked Bride: 641M plays The Alpha's Bride: 415M plays You can hear an example of our production quality here: https://pocketfm.com/show/ba2d9038fc3853c464c8be7a34a0576f26145106 We are proposing: License Fee: $17,500 Revenue Share: 15% of Revenue Exclusive serialized audio series adaptation rights (distinct from audiobook rights) English language (U.S./U.K.) 5-10 year term Full IP ownership retained by the author We are focused on long-term partnerships and would welcome discussion around additional titles within your catalog as well. If of interest, I'd be glad to schedule a brief call to discuss further. Best regards, Pulaksh Khimesara US Licensing & Commissioning Pocket FM | AV9: NOTE: Already contacted Sarina Bowen for: Hockey Guys, The Ivy Years, Hockey Guys
A10: P0 | B10: 75 | C10: Carolina Comets | D10: Teagan Hunter | E10: 30.48 | F10: 7 | G10: Puck Shy | H10: Neutral Zone | I10: 4.01 | J10: 20910 | K10: Tier 1 (>=20k) | L10: 0.4451 | M10: MODERATE 30-50% | N10: Ice Hockey / Sports Romance | O10: Long Series | P10: Before 2020 | Q10: Amazon Top 50 | R10: Amazon Top 50 | U10: Needgap | V10: 10 | W10: 10000 | X10: 12% | Y10: 12% - 18% | Z10: BELOW LENGTH THRESHOLD | AA10: Teagan Hunter | AB10: Self-Pub | AC10: teagan@teaganhunterwrites.com | AD10: FALSE | AE10: imberly@parkfinebrower.com | AF10: Park, Fine, and Brower Literary Management | AG10: http://teaganhunterwrites.com/ | AH10: Agent: Park, Fine, and Brower Literary Management | Website: http://teaganhunterwrites.com/ | AI10: sent | AJ10: 46207 | AP10: YELLOW | AQ10: Dear Teagan, I'm reaching out from Pocket FM regarding the Carolina Comets series. We believe this series has strong potential for adaptation into serialized audio, a rapidly growing format structurally distinct from traditional audiobooks. We'd like to propose a partnership that includes a License Fee of Revenue Share Only and 12% share of Revenue, details on the full offer are below. We understand many authors have granted exclusive audiobook rights (often to Audible). We are not seeking audiobook rights. Instead, we license serialized audio series adaptation rights, which are closer in nature to a TV dramatization, but in audio form, than to a traditional narrated audiobook. Rather than recording the manuscript verbatim, we create a scripted, episodic adaptation featuring dual-cast or full-cast performances, cinematic sound design, and structured cliffhanger arcs. Episodes run ~10 minutes and are released serially, with progression-based monetization. This format functions as an incremental revenue stream alongside print, ebook, KU, and audiobook sales, not in competition with them. Given the layered world-building and sustained narrative momentum in Carolina Comets, we see strong alignment with this dramatized serialized format. Pocket FM is the world's largest dedicated audio series platform, trusted by leading publishers and IP holders including Naver, Kakao, Blackstone, Recorded Books, Aethon, and China Literature. Our catalog includes globally recognized titles such as Solo Leveling, The Primal Hunter, and Omniscient Reader's Viewpoint. In the past 12 months, we've delivered: 120 billion minutes of listening 18 million monthly active users $342M in revenue 200+ million global downloads Our app is rated 4.7 on the App Store and 4.5 on Google Play. Several titles have scaled meaningfully through this model, including: My Vampire System: 1B+ listens, $100M+ revenue Saving Nora: $42M revenue The Duke's Masked Bride: 641M plays The Alpha's Bride: 415M plays You can hear an example of our production quality here: https://pocketfm.com/show/ba2d9038fc3853c464c8be7a34a0576f26145106 We are proposing: License Fee: Revenue Share Only Revenue Share: 12% of Revenue Exclusive serialized audio series adaptation rights (distinct from audiobook rights) English language (U.S./U.K.) 5-10 year term Full IP ownership retained by the author We are focused on long-term partnerships and would welcome discussion around additional titles within your catalog as well. If of interest, I'd be glad to schedule a brief call to discuss further. Best regards, Pulaksh Khimesara US Licensing & Commissioning Pocket FM
A11: P1 | B11: 59 | C11: Nashville Assassins | D11: Toni Aleo | E11: 83.97 | F11: 12 | G11: Breaking Away | H11: How We Fell in Love | I11: 4.21 | J11: 8182 | K11: Tier 2 (>=5k) | M11: WEAK <30% | N11: Ice Hockey / Sports Romance | O11: Long Series | P11: Before 2020 | U11: Needgap | V11: 5 | W11: 12500 | X11: 15% | Y11: 15% - 20% | Z11: READY | AA11: Toni Aleo | AB11: Self-Pub | AC11: toni@tonialeo.com | AD11: TRUE | AE11: info@nyliterary.com | AF11: Sarah Elizabeth Younger | AG11: https://tonialeo.com/ | AH11: Email: toni@tonialeo.com | Website: https://tonialeo.com/ | AI11: sent to toni and her agency | AJ11: 46177 | AP11: GREEN | AQ11: Dear Toni, I'm reaching out from Pocket FM regarding the Nashville Assassins series. We believe this series has strong potential for adaptation into serialized audio, a rapidly growing format structurally distinct from traditional audiobooks. We'd like to propose a partnership that includes a License Fee of $17,500 and 15% share of Revenue, details on the full offer are below. We understand many authors have granted exclusive audiobook rights (often to Audible). We are not seeking audiobook rights. Instead, we license serialized audio series adaptation rights, which are closer in nature to a TV dramatization, but in audio form, than to a traditional narrated audiobook. Rather than recording the manuscript verbatim, we create a scripted, episodic adaptation featuring dual-cast or full-cast performances, cinematic sound design, and structured cliffhanger arcs. Episodes run ~10 minutes and are released serially, with progression-based monetization. This format functions as an incremental revenue stream alongside print, ebook, KU, and audiobook sales, not in competition with them. Given the layered world-building and sustained narrative momentum in Nashville Assassins, we see strong alignment with this dramatized serialized format. Pocket FM is the world's largest dedicated audio series platform, trusted by leading publishers and IP holders including Naver, Kakao, Blackstone, Recorded Books, Aethon, and China Literature. Our catalog includes globally recognized titles such as Solo Leveling, The Primal Hunter, and Omniscient Reader's Viewpoint. In the past 12 months, we've delivered: 120 billion minutes of listening 18 million monthly active users $342M in revenue 200+ million global downloads Our app is rated 4.7 on the App Store and 4.5 on Google Play. Several titles have scaled meaningfully through this model, including: My Vampire System: 1B+ listens, $100M+ revenue Saving Nora: $42M revenue The Duke's Masked Bride: 641M plays The Alpha's Bride: 415M plays You can hear an example of our production quality here: https://pocketfm.com/show/ba2d9038fc3853c464c8be7a34a0576f26145106 We are proposing: License Fee: $17,500 Revenue Share: 15% of Revenue Exclusive serialized audio series adaptation rights (distinct from audiobook rights) English language (U.S./U.K.) 5-10 year term Full IP ownership retained by the author We are focused on long-term partnerships and would welcome discussion around additional titles within your catalog as well. If of interest, I'd be glad to schedule a brief call to discuss further. Best regards, Pulaksh Khimesara US Licensing & Commissioning Pocket FM | AV11: NOTE: Already contacted Toni Aleo for: Assassins
A12: P1 | B12: 55 | C12: Cold Fury Hockey | D12: Sawyer Bennett | E12: 102.9 | F12: 12 | G12: Alex | H12: Marek | I12: 3.93 | J12: 28682 | K12: Tier 1 (>=20k) | M12: WEAK <30% | N12: Ice Hockey / Sports Romance | O12: Long Series | P12: Before 2020 | U12: Needgap | V12: 1 | W12: 10000 | X12: 15% | Y12: 15% - 22% | Z12: READY | AA12: Loveswept | AB12: Indie | AC12: sawyer@sawyerbennett.com | AD12: TRUE | AF12: Contact form on official website | AG12: https://sawyerbennett.com | AH12: Email: sawyer@sawyerbennett.com | Agent: Contact form on official website | Website: https://sawyerbennett.com | AI12: =vlookup(C12,'Az working sheet Hockey Sports'!A:AT,45,0) | AJ12: 46177 | AP12: GREEN | AQ12: Dear Sawyer, I'm reaching out from Pocket FM regarding the Cold Fury Hockey series. We believe this series has strong potential for adaptation into serialized audio, a rapidly growing format structurally distinct from traditional audiobooks. We'd like to propose a partnership that includes a License Fee of $25,000 and 15% share of Revenue, details on the full offer are below. We understand many authors have granted exclusive audiobook rights (often to Audible). We are not seeking audiobook rights. Instead, we license serialized audio series adaptation rights, which are closer in nature to a TV dramatization, but in audio form, than to a traditional narrated audiobook. Rather than recording the manuscript verbatim, we create a scripted, episodic adaptation featuring dual-cast or full-cast performances, cinematic sound design, and structured cliffhanger arcs. Episodes run ~10 minutes and are released serially, with progression-based monetization. This format functions as an incremental revenue stream alongside print, ebook, KU, and audiobook sales, not in competition with them. Given the layered world-building and sustained narrative momentum in Cold Fury Hockey, we see strong alignment with this dramatized serialized format. Pocket FM is the world's largest dedicated audio series platform, trusted by leading publishers and IP holders including Naver, Kakao, Blackstone, Recorded Books, Aethon, and China Literature. Our catalog includes globally recognized titles such as Solo Leveling, The Primal Hunter, and Omniscient Reader's Viewpoint. In the past 12 months, we've delivered: 120 billion minutes of listening 18 million monthly active users $342M in revenue 200+ million global downloads Our app is rated 4.7 on the App Store and 4.5 on Google Play. Several titles have scaled meaningfully through this model, including: My Vampire System: 1B+ listens, $100M+ revenue Saving Nora: $42M revenue The Duke's Masked Bride: 641M plays The Alpha's Bride: 415M plays You can hear an example of our production quality here: https://pocketfm.com/show/ba2d9038fc3853c464c8be7a34a0576f26145106 We are proposing: License Fee: $25,000 Revenue Share: 15% of Revenue Exclusive serialized audio series adaptation rights (distinct from audiobook rights) English language (U.S./U.K.) 5-10 year term Full IP ownership retained by the author We are focused on long-term partnerships and would welcome discussion around additional titles within your catalog as well. If of interest, I'd be glad to schedule a brief call to discuss further. Best regards, Pulaksh Khimesara US Licensing & Commissioning Pocket FM | AV12: NOTE: Already contacted Sawyer Bennett for: Arizona Vengeance
A13: P5 | B13: 58 | C13: Knight's Journal | D13: Brian J. Lang | E13: 3.12 | F13: 12 | G13: Knight Descendent | H13: Knight Ascendent | I13: 5 | J13: 2 | K13: Tier 3 (<5k) | L13: 1 | M13: STRONG >=50% | N13: Ice Hockey / Sports Romance | O13: Standalone | P13: Before 2020 | U13: Needgap | V13: 10 | W13: No MG | X13: 12% | Y13: 12% - 18% | Z13: BELOW LENGTH THRESHOLD | AA13: Self-Published (Brian J. Lang) | AB13: Self-Pub | AC13: witchking701@gmail.com | AD13: TRUE | AE13: witchking701@gmail.com | AG13: https://witchking701.wixsite.com/brianjlang | AH13: Email: witchking701@gmail.com | Agent email: witchking701@gmail.com | Website: https://witchking701.wixsite.com/brianjlang | AI13: irrelevant | AJ13: 46207 | AP13: GREEN | AQ13: Dear Brian, I'm reaching out from Pocket FM regarding the Knight's Journal series. We believe this series has strong potential for adaptation into serialized audio, a rapidly growing format structurally distinct from traditional audiobooks. We'd like to propose a partnership that includes a License Fee of Revenue Share Only and 12% share of Revenue, details on the full offer are below. We understand many authors have granted exclusive audiobook rights (often to Audible). We are not seeking audiobook rights. Instead, we license serialized audio series adaptation rights, which are closer in nature to a TV dramatization, but in audio form, than to a traditional narrated audiobook. Rather than recording the manuscript verbatim, we create a scripted, episodic adaptation featuring dual-cast or full-cast performances, cinematic sound design, and structured cliffhanger arcs. Episodes run ~10 minutes and are released serially, with progression-based monetization. This format functions as an incremental revenue stream alongside print, ebook, KU, and audiobook sales, not in competition with them. Given the layered world-building and sustained narrative momentum in Knight's Journal, we see strong alignment with this dramatized serialized format. Pocket FM is the world's largest dedicated audio series platform, trusted by leading publishers and IP holders including Naver, Kakao, Blackstone, Recorded Books, Aethon, and China Literature. Our catalog includes globally recognized titles such as Solo Leveling, The Primal Hunter, and Omniscient Reader's Viewpoint. In the past 12 months, we've delivered: 120 billion minutes of listening 18 million monthly active users $342M in revenue 200+ million global downloads Our app is rated 4.7 on the App Store and 4.5 on Google Play. Several titles have scaled meaningfully through this model, including: My Vampire System: 1B+ listens, $100M+ revenue Saving Nora: $42M revenue The Duke's Masked Bride: 641M plays The Alpha's Bride: 415M plays You can hear an example of our production quality here: https://pocketfm.com/show/ba2d9038fc3853c464c8be7a34a0576f26145106 We are proposing: License Fee: Revenue Share Only Revenue Share: 12% of Revenue Exclusive serialized audio series adaptation rights (distinct from audiobook rights) English language (U.S./U.K.) 5-10 year term Full IP ownership retained by the author We are focused on long-term partnerships and would welcome discussion around additional titles within your catalog as well. If of interest, I'd be glad to schedule a brief call to discuss further. Best regards, Pulaksh Khimesara US Licensing & Commissioning Pocket FM | AR13: witchking701@gmail.com | AS13: author_email | AT13: https://witchking701.wixsite.com/brianjlang | AU13: High
A14: P0 | B14: 70 | C14: Wildcat Hockey | D14: Rebecca Jenshak | E14: 59.97 | F14: 5 | G14: Wildcat | H14: Forever Wild | I14: 3.83 | J14: 22561 | K14: Tier 1 (>=20k) | M14: WEAK <30% | N14: Ice Hockey / Sports Romance | O14: Series | P14: After 2020 | U14: Needgap | V14: 2 | W14: $17,500 - $20,000 | X14: 15% | Y14: 15% - 22% | Z14: NEED CONTACT | AA14: Rebecca Jenshak | AB14: Self-Pub | AD14: FALSE | AE14: georgana@theseymouragency.com | AF14: Contact form on official website | AG14: https://rebeccajenshak.com | AH14: Agent: Contact form on official website | Website: https://rebeccajenshak.com | AI14: sent | AJ14: 46207 | AP14: YELLOW
A15: P0 | B15: 50 | C15: Pucked | D15: Helena Hunting | E15: 95.67 | F15: 11 | G15: Pucked LAST: Where It Begins URL: UNKNOWN | H15: Where It Begins URL: UNKNOWN | I15: 4.5 | J15: 91324 | K15: Tier 3 (<5k) | L15: 1.4203 | M15: STRONG >=50% | N15: Ice Hockey / Sports Romance | O15: Long Series | P15: After 2020 | U15: Needgap | V15: 9 | W15: 10000 | X15: 0.15 | Y15: 12% - 18% | Z15: READY (low ratings) | AA15: Helena Hunting | AB15: Self-Pub | AC15: kbrower@parkfinebrower.com | AD15: TRUE | AE15: kbrower@parkfinebrower.com | AF15: Kimberly Brower of | AG15: http://www.helenahunting.com/ | AH15: Email: kbrower@parkfinebrower.com | Agent email: kbrower@parkfinebrower.com | Agent: Kimberly Brower of | Website: http://www.helenahunting.com/ | AI15: sent to kimberly and helena | AJ15: 46177 | AP15: GREEN | AQ15: Dear Helena, I'm reaching out from Pocket FM regarding the Pucked series. We believe this series has strong potential for adaptation into serialized audio, a rapidly growing format structurally distinct from traditional audiobooks. We'd like to propose a partnership that includes a License Fee of $1,000 and 12% share of Revenue, details on the full offer are below. We understand many authors have granted exclusive audiobook rights (often to Audible). We are not seeking audiobook rights. Instead, we license serialized audio series adaptation rights, which are closer in nature to a TV dramatization, but in audio form, than to a traditional narrated audiobook. Rather than recording the manuscript verbatim, we create a scripted, episodic adaptation featuring dual-cast or full-cast performances, cinematic sound design, and structured cliffhanger arcs. Episodes run ~10 minutes and are released serially, with progression-based monetization. This format functions as an incremental revenue stream alongside print, ebook, KU, and audiobook sales, not in competition with them. Given the layered world-building and sustained narrative momentum in Pucked, we see strong alignment with this dramatized serialized format. Pocket FM is the world's largest dedicated audio series platform, trusted by leading publishers and IP holders including Naver, Kakao, Blackstone, Recorded Books, Aethon, and China Literature. Our catalog includes globally recognized titles such as Solo Leveling, The Primal Hunter, and Omniscient Reader's Viewpoint. In the past 12 months, we've delivered: 120 billion minutes of listening 18 million monthly active users $342M in revenue 200+ million global downloads Our app is rated 4.7 on the App Store and 4.5 on Google Play. Several titles have scaled meaningfully through this model, including: My Vampire System: 1B+ listens, $100M+ revenue Saving Nora: $42M revenue The Duke's Masked Bride: 641M plays The Alpha's Bride: 415M plays You can hear an example of our production quality here: https://pocketfm.com/show/ba2d9038fc3853c464c8be7a34a0576f26145106 We are proposing: License Fee: $1,000 Revenue Share: 12% of Revenue Exclusive serialized audio series adaptation rights (distinct from audiobook rights) English language (U.S./U.K.) 5-10 year term Full IP ownership retained by the author We are focused on long-term partnerships and would welcome discussion around additional titles within your catalog as well. If of interest, I'd be glad to schedule a brief call to discuss further. Best regards, Pulaksh Khimesara US Licensing & Commissioning Pocket FM | AV15: NOTE: Already contacted Helena Hunting for: All In
A16: P0 | B16: 65 | C16: Sweater Weather | D16: Emma St. Clair | E16: 64.26 | F16: 7 | G16: Just Don't Fall | H16: Absolutely Not in Love | I16: 3.93 | J16: 22698 | K16: Tier 1 (>=20k) | M16: WEAK <30% | N16: Ice Hockey / Sports Romance | O16: Long Series | P16: Before 2020 | U16: Needgap | V16: 2 | W16: $17,500 - $20,000 | X16: 15% | Y16: 15% - 22% | Z16: NEED CONTACT | AA16: Create If Writing LLC | AB16: Self-Pub | AC16: emma@emmastclair.com | AD16: FALSE | AE16: kwhalen@thewhalenagency.com | AF16: NONE WEBSITE: emmastclair.com | AG16: https://emmastclair.com/ | AH16: Agent: NONE WEBSITE: emmastclair.com | Website: https://emmastclair.com/ | AI16: sent | AJ16: 46207 | AP16: YELLOW
A17: P0 | B17: 60 | C17: Love and Hockey | D17: Nikki Lawson | E17: 193.5 | F17: 6 | G17: Offside Hearts | H17: Goal Line Hearts | I17: 3.88 | J17: 27482 | K17: Tier 1 (>=20k) | M17: WEAK <30% | N17: Ice Hockey / Sports Romance | O17: Long Series | P17: After 2020 | U17: Needgap | V17: 1 | W17: $17,500 - $25,000 | X17: 15% | Y17: 15% - 22% | Z17: NEED CONTACT | AA17: Lauren Blakely Books | AB17: Self-Pub | AD17: FALSE | AG17: https://nikki-lawson.com/ | AH17: Website: https://nikki-lawson.com/ | AI17: couldnt find email | AP17: YELLOW | AS17: not_found | AT17: https://www.fantasticfiction.com/l/nikki-lawson/ | AU17: Not Found | AV17: TikTok/FB presence only. No public email found.
A18: P0 | B18: 60 | C18: Carolina Reapers | D18: Samantha Whiskey | E18: 86.4 | F18: 10 | G18: Axel | H18: Maxim | I18: 4.03 | J18: 12450 | K18: Tier 2 (>=5k) | L18: 0.4439 | M18: MODERATE 30-50% | N18: Ice Hockey / Sports Romance | O18: Long Series | P18: Before 2020 | U18: Needgap | V18: 5 | W18: $12,500 - $17,500 | X18: 15% | Y18: 15% - 20% | Z18: NEED CONTACT | AA18: Samantha Whiskey | AB18: Indie | AD18: FALSE | AG18: http://eepurl.com/bSQRWr | AH18: Website: http://eepurl.com/bSQRWr | AI18: couldnt find email | AP18: YELLOW | AS18: contact_form_url | AT18: https://linktr.ee/samanthawhiskey | AU18: Not Found | AV18: Linktree profile. Mailing list: eepurl.com/bSQRWr. No direct email. | Audit note: normalized row to validated contact state.
A19: P5 | B19: 58 | C19: Arizona Vengeance | D19: Sawyer Bennett | E19: 92.79 | F19: 11 | G19: Bishop | H19: Riggs | I19: 4.04 | J19: 5243 | K19: Tier 2 (>=5k) | L19: 0.7738 | M19: STRONG >=50% | N19: Ice Hockey / Sports Romance | O19: Long Series | P19: Before 2020 | U19: Needgap | V19: 5 | W19: 4000 | X19: 0.15 | Y19: 15% - 20% | Z19: READY | AA19: Big Dog Books, LLC | AB19: Indie | AC19: sawyer@sawyerbennett.com | AD19: TRUE | AF19: Contact form on official website | AG19: https://sawyerbennett.com | AH19: Email: sawyer@sawyerbennett.com | Agent: Contact form on official website | Website: https://sawyerbennett.com | AI19: sent to sawyer bennet (other titles) | AJ19: 46207 | AP19: GREEN | AQ19: Dear Sawyer, I'm reaching out from Pocket FM regarding the Arizona Vengeance series. We believe this series has strong potential for adaptation into serialized audio, a rapidly growing format structurally distinct from traditional audiobooks. We'd like to propose a partnership that includes a License Fee of $17,500 and 15% share of Revenue, details on the full offer are below. We understand many authors have granted exclusive audiobook rights (often to Audible). We are not seeking audiobook rights. Instead, we license serialized audio series adaptation rights, which are closer in nature to a TV dramatization, but in audio form, than to a traditional narrated audiobook. Rather than recording the manuscript verbatim, we create a scripted, episodic adaptation featuring dual-cast or full-cast performances, cinematic sound design, and structured cliffhanger arcs. Episodes run ~10 minutes and are released serially, with progression-based monetization. This format functions as an incremental revenue stream alongside print, ebook, KU, and audiobook sales, not in competition with them. Given the layered world-building and sustained narrative momentum in Arizona Vengeance, we see strong alignment with this dramatized serialized format. Pocket FM is the world's largest dedicated audio series platform, trusted by leading publishers and IP holders including Naver, Kakao, Blackstone, Recorded Books, Aethon, and China Literature. Our catalog includes globally recognized titles such as Solo Leveling, The Primal Hunter, and Omniscient Reader's Viewpoint. In the past 12 months, we've delivered: 120 billion minutes of listening 18 million monthly active users $342M in revenue 200+ million global downloads Our app is rated 4.7 on the App Store and 4.5 on Google Play. Several titles have scaled meaningfully through this model, including: My Vampire System: 1B+ listens, $100M+ revenue Saving Nora: $42M revenue The Duke's Masked Bride: 641M plays The Alpha's Bride: 415M plays You can hear an example of our production quality here: https://pocketfm.com/show/ba2d9038fc3853c464c8be7a34a0576f26145106 We are proposing: License Fee: $17,500 Revenue Share: 15% of Revenue Exclusive serialized audio series adaptation rights (distinct from audiobook rights) English language (U.S./U.K.) 5-10 year term Full IP ownership retained by the author We are focused on long-term partnerships and would welcome discussion around additional titles within your catalog as well. If of interest, I'd be glad to schedule a brief call to discuss further. Best regards, Pulaksh Khimesara US Licensing & Commissioning Pocket FM
A20: P0 | B20: 50 | C20: Seattle Sharks | D20: Samantha Whiskey | E20: 312.3 | F20: 9 | G20: Grinder | H20: Defender | I20: 3.92 | J20: 11759 | K20: Tier 2 (>=5k) | L20: 0.3174 | M20: MODERATE 30-50% | N20: Ice Hockey / Sports Romance | O20: Long Series | P20: Before 2020 | U20: Needgap | V20: 5 | W20: $12,500 - $17,500 | X20: 15% | Y20: 15% - 20% | Z20: NEED CONTACT | AA20: Samantha Whiskey | AB20: Indie | AD20: FALSE | AG20: http://eepurl.com/bSQRWr | AH20: Website: http://eepurl.com/bSQRWr | AI20: couldnt find email | AP20: YELLOW | AS20: contact_form_url | AT20: https://linktr.ee/samanthawhiskey | AU20: Not Found | AV20: Linktree profile. Mailing list: eepurl.com/bSQRWr. No direct email. | Audit note: normalized row to validated contact state.
A21: P0 | B21: 70 | C21: Vancouver Wolves Hockey | D21: Odette Stone | E21: 45.9 | F21: 4 | G21: Puck Me Secretly | H21: High Risk Rookie | I21: 3.93 | J21: 49156 | K21: Tier 1 (>=20k) | L21: 0.3168 | M21: MODERATE 30-50% | N21: Ice Hockey / Sports Romance | O21: Series | P21: Before 2020 | U21: Needgap | V21: 2 | W21: 3000 | X21: 15% | Y21: 15% - 22% | Z21: READY | AA21: Odette Stone Publishing Inc. | AB21: Self-Pub | AC21: odette.stone@yahoo.com | AD21: TRUE | AF21: Odette Stone currently does not have a literary agent. | AG21: http://www.odettestone.com | AH21: Email: odette.stone@yahoo.com | Agent: Odette Stone currently does not have a literary agent. | Website: http://www.odettestone.com | AI21: sent to odette stone | AJ21: 46177 | AP21: GREEN | AQ21: Dear Odette, I'm reaching out from Pocket FM regarding the Vancouver Wolves Hockey series. We believe this series has strong potential for adaptation into serialized audio, a rapidly growing format structurally distinct from traditional audiobooks. We'd like to propose a partnership that includes a License Fee of $20,000 and 15% share of Revenue, details on the full offer are below. We understand many authors have granted exclusive audiobook rights (often to Audible). We are not seeking audiobook rights. Instead, we license serialized audio series adaptation rights, which are closer in nature to a TV dramatization, but in audio form, than to a traditional narrated audiobook. Rather than recording the manuscript verbatim, we create a scripted, episodic adaptation featuring dual-cast or full-cast performances, cinematic sound design, and structured cliffhanger arcs. Episodes run ~10 minutes and are released serially, with progression-based monetization. This format functions as an incremental revenue stream alongside print, ebook, KU, and audiobook sales, not in competition with them. Given the layered world-building and sustained narrative momentum in Vancouver Wolves Hockey, we see strong alignment with this dramatized serialized format. Pocket FM is the world's largest dedicated audio series platform, trusted by leading publishers and IP holders including Naver, Kakao, Blackstone, Recorded Books, Aethon, and China Literature. Our catalog includes globally recognized titles such as Solo Leveling, The Primal Hunter, and Omniscient Reader's Viewpoint. In the past 12 months, we've delivered: 120 billion minutes of listening 18 million monthly active users $342M in revenue 200+ million global downloads Our app is rated 4.7 on the App Store and 4.5 on Google Play. Several titles have scaled meaningfully through this model, including: My Vampire System: 1B+ listens, $100M+ revenue Saving Nora: $42M revenue The Duke's Masked Bride: 641M plays The Alpha's Bride: 415M plays You can hear an example of our production quality here: https://pocketfm.com/show/ba2d9038fc3853c464c8be7a34a0576f26145106 We are proposing: License Fee: $20,000 Revenue Share: 15% of Revenue Exclusive serialized audio series adaptation rights (distinct from audiobook rights) English language (U.S./U.K.) 5-10 year term Full IP ownership retained by the author We are focused on long-term partnerships and would welcome discussion around additional titles within your catalog as well. If of interest, I'd be glad to schedule a brief call to discuss further. Best regards, Pulaksh Khimesara US Licensing & Commissioning Pocket FM
A22: P0 | B22: 48 | C22: Playing to Win | D22: Bella Matthews | E22: 51 | F22: 4 | G22: The Keeper | H22: The Sweet Spot | I22: 3.96 | J22: 17756 | K22: Tier 2 (>=5k) | L22: 0.4331 | M22: MODERATE 30-50% | N22: Ice Hockey / Sports Romance | O22: Series | P22: After 2020 | S22: Sports Romance (Paid) #78 | T22: 78 | U22: Needgap | V22: 6 | W22: $5,000 - $7,500 | X22: 15% | Y22: 15% - 20% | Z22: READY | AA22: Bella Matthews | AB22: Indie | AC22: Brianna@authorbellamatthews.com | AD22: TRUE | AF22: The Seymour Agency | AG22: https://bellamatthews.com/ | AH22: Email: Brianna@authorbellamatthews.com | Agent: The Seymour Agency | Website: https://bellamatthews.com/ | AI22: sent to bella and georgana | AJ22: 46177 | AP22: GREEN | AQ22: Dear Bella, I'm reaching out from Pocket FM regarding the Playing to Win series. We believe this series has strong potential for adaptation into serialized audio, a rapidly growing format structurally distinct from traditional audiobooks. We'd like to propose a partnership that includes a License Fee of $7,500 and 15% share of Revenue, details on the full offer are below. We understand many authors have granted exclusive audiobook rights (often to Audible). We are not seeking audiobook rights. Instead, we license serialized audio series adaptation rights, which are closer in nature to a TV dramatization, but in audio form, than to a traditional narrated audiobook. Rather than recording the manuscript verbatim, we create a scripted, episodic adaptation featuring dual-cast or full-cast performances, cinematic sound design, and structured cliffhanger arcs. Episodes run ~10 minutes and are released serially, with progression-based monetization. This format functions as an incremental revenue stream alongside print, ebook, KU, and audiobook sales, not in competition with them. Given the layered world-building and sustained narrative momentum in Playing to Win, we see strong alignment with this dramatized serialized format. Pocket FM is the world's largest dedicated audio series platform, trusted by leading publishers and IP holders including Naver, Kakao, Blackstone, Recorded Books, Aethon, and China Literature. Our catalog includes globally recognized titles such as Solo Leveling, The Primal Hunter, and Omniscient Reader's Viewpoint. In the past 12 months, we've delivered: 120 billion minutes of listening 18 million monthly active users $342M in revenue 200+ million global downloads Our app is rated 4.7 on the App Store and 4.5 on Google Play. Several titles have scaled meaningfully through this model, including: My Vampire System: 1B+ listens, $100M+ revenue Saving Nora: $42M revenue The Duke's Masked Bride: 641M plays The Alpha's Bride: 415M plays You can hear an example of our production quality here: https://pocketfm.com/show/ba2d9038fc3853c464c8be7a34a0576f26145106 We are proposing: License Fee: $7,500 Revenue Share: 15% of Revenue Exclusive serialized audio series adaptation rights (distinct from audiobook rights) English language (U.S./U.K.) 5-10 year term Full IP ownership retained by the author We are focused on long-term partnerships and would welcome discussion around additional titles within your catalog as well. If of interest, I'd be glad to schedule a brief call to discuss further. Best regards, Pulaksh Khimesara US Licensing & Commissioning Pocket FM | AV22: NOTE: Already contacted Bella Matthews for: Defiant Kings
A23: P0 | C23: The Vancouver Agitators | D23: Meghan Quinn | E23: 69.45 | F23: 5 | G23: Kiss and Don't Tell | H23: So This Is War | I23: 3.99 | J23: 89096 | K23: Tier 1 (>=20k) | M23: WEAK <30% | N23: Ice Hockey / Sports Romance | O23: Series | P23: After 2020 | S23: Sports Romance (Paid) #5 | T23: 5 | U23: Needgap | V23: 2 | W23: $17,500 - $20,000 | X23: 15% | Y23: 15% - 22% | Z23: READY | AA23: Meghan Quinn | AB23: Indie | AC23: admin@authormeghanquinn.com | AD23: FALSE | AE23: flavia@bookcaseagency.com | AF23: Flavia Viotti, Bookcase Agency | AG23: https://meghanquinnauthor.com | AH23: Agent email: admin@authormeghanquinn.com | Agent: Flavia Viotti, Bookcase Agency | Website: https://meghanquinnauthor.com | AI23: sent | AP23: YELLOW | AQ23: Dear Meghan, I'm reaching out from Pocket FM regarding the The Agitators Series series. We believe this series has strong potential for adaptation into serialized audio, a rapidly growing format structurally distinct from traditional audiobooks. We'd like to propose a partnership that includes a License Fee of $20,000 and 15% share of Revenue, details on the full offer are below. We understand many authors have granted exclusive audiobook rights (often to Audible). We are not seeking audiobook rights. Instead, we license serialized audio series adaptation rights, which are closer in nature to a TV dramatization, but in audio form, than to a traditional narrated audiobook. Rather than recording the manuscript verbatim, we create a scripted, episodic adaptation featuring dual-cast or full-cast performances, cinematic sound design, and structured cliffhanger arcs. Episodes run ~10 minutes and are released serially, with progression-based monetization. This format functions as an incremental revenue stream alongside print, ebook, KU, and audiobook sales, not in competition with them. Given the layered world-building and sustained narrative momentum in The Agitators Series, we see strong alignment with this dramatized serialized format. Pocket FM is the world's largest dedicated audio series platform, trusted by leading publishers and IP holders including Naver, Kakao, Blackstone, Recorded Books, Aethon, and China Literature. Our catalog includes globally recognized titles such as Solo Leveling, The Primal Hunter, and Omniscient Reader's Viewpoint. In the past 12 months, we've delivered: 120 billion minutes of listening 18 million monthly active users $342M in revenue 200+ million global downloads Our app is rated 4.7 on the App Store and 4.5 on Google Play. Several titles have scaled meaningfully through this model, including: My Vampire System: 1B+ listens, $100M+ revenue Saving Nora: $42M revenue The Duke's Masked Bride: 641M plays The Alpha's Bride: 415M plays You can hear an example of our production quality here: https://pocketfm.com/show/ba2d9038fc3853c464c8be7a34a0576f26145106 We are proposing: License Fee: $20,000 Revenue Share: 15% of Revenue Exclusive serialized audio series adaptation rights (distinct from audiobook rights) English language (U.S./U.K.) 5-10 year term Full IP ownership retained by the author We are focused on long-term partnerships and would welcome discussion around additional titles within your catalog as well. If of interest, I'd be glad to schedule a brief call to discuss further. Best regards, Pulaksh Khimesara US Licensing & Commissioning Pocket FM
A24: P1 | B24: 85 | C24: Playing for Keeps | D24: Becka Mack | E24: 155.1 | F24: 5 | G24: Consider Me | H24: Breathe With Me | I24: 3.83 | J24: 230122 | K24: Tier 1 (>=20k) | L24: 0.1445 | M24: WEAK <30% | N24: Ice Hockey / Sports Romance | O24: Series | P24: After 2020 | Q24: Sports T100 | R24: Sports T100 | U24: Needgap | V24: 1 | W24: $17,500 - $25,000 | X24: 15% | Y24: 15% - 22% | Z24: READY | AA24: Becka Mack | AB24: Indie | AC24: info@beckamack.com | AD24: TRUE | AE24: pknapp@parkfine.com | AF24: Peter Knapp and Stuti Telidevara, Park Fine & Brower | AG24: https://www.beckamack.com/ | AH24: Email: info@beckamack.com | Agent email: pknapp@parkfine.com | Agent: Peter Knapp and Stuti Telidevara, Park Fine & Brower | Website: https://www.beckamack.com/ | AI24: =vlookup(C24,'Az working sheet Hockey Sports'!A:AT,45,0) | AP24: YELLOW | AQ24: Dear Becka, I'm reaching out from Pocket FM regarding the Playing for Keeps series. We believe this series has strong potential for adaptation into serialized audio, a rapidly growing format structurally distinct from traditional audiobooks. We'd like to propose a partnership that includes a License Fee of $25,000 and 15% share of Revenue, details on the full offer are below. We understand many authors have granted exclusive audiobook rights (often to Audible). We are not seeking audiobook rights. Instead, we license serialized audio series adaptation rights, which are closer in nature to a TV dramatization, but in audio form, than to a traditional narrated audiobook. Rather than recording the manuscript verbatim, we create a scripted, episodic adaptation featuring dual-cast or full-cast performances, cinematic sound design, and structured cliffhanger arcs. Episodes run ~10 minutes and are released serially, with progression-based monetization. This format functions as an incremental revenue stream alongside print, ebook, KU, and audiobook sales, not in competition with them. Given the layered world-building and sustained narrative momentum in Playing for Keeps, we see strong alignment with this dramatized serialized format. Pocket FM is the world's largest dedicated audio series platform, trusted by leading publishers and IP holders including Naver, Kakao, Blackstone, Recorded Books, Aethon, and China Literature. Our catalog includes globally recognized titles such as Solo Leveling, The Primal Hunter, and Omniscient Reader's Viewpoint. In the past 12 months, we've delivered: 120 billion minutes of listening 18 million monthly active users $342M in revenue 200+ million global downloads Our app is rated 4.7 on the App Store and 4.5 on Google Play. Several titles have scaled meaningfully through this model, including: My Vampire System: 1B+ listens, $100M+ revenue Saving Nora: $42M revenue The Duke's Masked Bride: 641M plays The Alpha's Bride: 415M plays You can hear an example of our production quality here: https://pocketfm.com/show/ba2d9038fc3853c464c8be7a34a0576f26145106 We are proposing: License Fee: $25,000 Revenue Share: 15% of Revenue Exclusive serialized audio series adaptation rights (distinct from audiobook rights) English language (U.S./U.K.) 5-10 year term Full IP ownership retained by the author We are focused on long-term partnerships and would welcome discussion around additional titles within your catalog as well. If of interest, I'd be glad to schedule a brief call to discuss further. Best regards, Pulaksh Khimesara US Licensing & Commissioning Pocket FM
A25: P5 | B25: 40 | C25: Boys of Winter | D25: S.R. Grey | E25: 9.48 | F25: 11 | G25: Destiny on Ice | H25: Risk on Ice | I25: 3.74 | J25: 2212 | K25: Tier 3 (<5k) | L25: 1 | M25: STRONG >=50% | N25: Ice Hockey / Sports Romance | O25: Long Series | P25: Before 2020 | U25: Needgap | V25: 10 | W25: No MG | X25: 12% | Y25: 12% - 18% | Z25: BELOW LENGTH THRESHOLD | AA25: S.R. Grey LLC | AB25: Self-Pub | AD25: TRUE | AF25: Ena Burnette | AG25: http://www.srgrey.com/ | AH25: Email: amanda@sbrmedia.com | Agent: Ena Burnette | Website: http://www.srgrey.com/ | AI25: =vlookup(C25,'Mail Merge'!B:J,9,0) | AJ25: 46207 | AP25: GREEN | AQ25: Dear S.R., I'm reaching out from Pocket FM regarding the Boys of Winter series. We believe this series has strong potential for adaptation into serialized audio, a rapidly growing format structurally distinct from traditional audiobooks. We'd like to propose a partnership that includes a License Fee of Revenue Share Only and 12% share of Revenue, details on the full offer are below. We understand many authors have granted exclusive audiobook rights (often to Audible). We are not seeking audiobook rights. Instead, we license serialized audio series adaptation rights, which are closer in nature to a TV dramatization, but in audio form, than to a traditional narrated audiobook. Rather than recording the manuscript verbatim, we create a scripted, episodic adaptation featuring dual-cast or full-cast performances, cinematic sound design, and structured cliffhanger arcs. Episodes run ~10 minutes and are released serially, with progression-based monetization. This format functions as an incremental revenue stream alongside print, ebook, KU, and audiobook sales, not in competition with them. Given the layered world-building and sustained narrative momentum in Boys of Winter, we see strong alignment with this dramatized serialized format. Pocket FM is the world's largest dedicated audio series platform, trusted by leading publishers and IP holders including Naver, Kakao, Blackstone, Recorded Books, Aethon, and China Literature. Our catalog includes globally recognized titles such as Solo Leveling, The Primal Hunter, and Omniscient Reader's Viewpoint. In the past 12 months, we've delivered: 120 billion minutes of listening 18 million monthly active users $342M in revenue 200+ million global downloads Our app is rated 4.7 on the App Store and 4.5 on Google Play. Several titles have scaled meaningfully through this model, including: My Vampire System: 1B+ listens, $100M+ revenue Saving Nora: $42M revenue The Duke's Masked Bride: 641M plays The Alpha's Bride: 415M plays You can hear an example of our production quality here: https://pocketfm.com/show/ba2d9038fc3853c464c8be7a34a0576f26145106 We are proposing: License Fee: Revenue Share Only Revenue Share: 12% of Revenue Exclusive serialized audio series adaptation rights (distinct from audiobook rights) English language (U.S./U.K.) 5-10 year term Full IP ownership retained by the author We are focused on long-term partnerships and would welcome discussion around additional titles within your catalog as well. If of interest, I'd be glad to schedule a brief call to discuss further. Best regards, Pulaksh Khimesara US Licensing & Commissioning Pocket FM | AS25: contact_form_url | AT25: https://srgrey.com | AU25: Not Found | AV25: Audit note: normalized row to validated contact state.
A26: P5 | B26: 35 | C26: New York Blades | D26: Deirdre Martin | E26: 99.78 | F26: 10 | G26: Body Check | H26: Hip Check | I26: 3.84 | J26: 4915 | K26: Tier 3 (<5k) | L26: 0.3003 | M26: MODERATE 30-50% | N26: Ice Hockey / Sports Romance | O26: Long Series | P26: Before 2020 | U26: Needgap | V26: 9 | W26: Up to $1,000 | X26: 12% | Y26: 12% - 18% | Z26: READY | AA26: Berkley | AB26: Big Pub | AC26: deirdre@deirdremartin.com | AD26: TRUE | AG26: http://www.deirdremartin.com | AH26: Email: deirdre@deirdremartin.com | Website: http://www.deirdremartin.com | AI26: =vlookup(C26,'Mail Merge'!B:J,9,0) | AJ26: 46207 | AP26: GREEN | AQ26: Dear Deirdre, I'm reaching out from Pocket FM regarding the New York Blades series. We believe this series has strong potential for adaptation into serialized audio, a rapidly growing format structurally distinct from traditional audiobooks. We'd like to propose a partnership that includes a License Fee of $1,000 and 12% share of Revenue, details on the full offer are below. We understand many authors have granted exclusive audiobook rights (often to Audible). We are not seeking audiobook rights. Instead, we license serialized audio series adaptation rights, which are closer in nature to a TV dramatization, but in audio form, than to a traditional narrated audiobook. Rather than recording the manuscript verbatim, we create a scripted, episodic adaptation featuring dual-cast or full-cast performances, cinematic sound design, and structured cliffhanger arcs. Episodes run ~10 minutes and are released serially, with progression-based monetization. This format functions as an incremental revenue stream alongside print, ebook, KU, and audiobook sales, not in competition with them. Given the layered world-building and sustained narrative momentum in New York Blades, we see strong alignment with this dramatized serialized format. Pocket FM is the world's largest dedicated audio series platform, trusted by leading publishers and IP holders including Naver, Kakao, Blackstone, Recorded Books, Aethon, and China Literature. Our catalog includes globally recognized titles such as Solo Leveling, The Primal Hunter, and Omniscient Reader's Viewpoint. In the past 12 months, we've delivered: 120 billion minutes of listening 18 million monthly active users $342M in revenue 200+ million global downloads Our app is rated 4.7 on the App Store and 4.5 on Google Play. Several titles have scaled meaningfully through this model, including: My Vampire System: 1B+ listens, $100M+ revenue Saving Nora: $42M revenue The Duke's Masked Bride: 641M plays The Alpha's Bride: 415M plays You can hear an example of our production quality here: https://pocketfm.com/show/ba2d9038fc3853c464c8be7a34a0576f26145106 We are proposing: License Fee: $1,000 Revenue Share: 12% of Revenue Exclusive serialized audio series adaptation rights (distinct from audiobook rights) English language (U.S./U.K.) 5-10 year term Full IP ownership retained by the author We are focused on long-term partnerships and would welcome discussion around additional titles within your catalog as well. If of interest, I'd be glad to schedule a brief call to discuss further. Best regards, Pulaksh Khimesara US Licensing & Commissioning Pocket FM
A27: P1 | B27: 48 | C27: Seattle Sockeyes Hockey | D27: Jami Davenport | E27: 122.25 | F27: 9 | G27: Skating on Thin Ice | H27: Deflected | I27: 3.76 | J27: 2142 | K27: Tier 3 (<5k) | L27: 0.2614 | M27: WEAK <30% | N27: Ice Hockey / Sports Romance | O27: Long Series | P27: Before 2020 | U27: Needgap | V27: 9 | W27: Up to $1,000 | X27: 12% | Y27: 12% - 18% | Z27: READY | AA27: Jami Davenport | AB27: Self-Pub | AC27: jamidavenport@hotmail.com | AD27: TRUE | AF27: SBR Media | AG27: https://www.jamidavenport.com/ | AH27: Email: jamidavenport@hotmail.com | Agent: SBR Media | Website: https://www.jamidavenport.com/ | AI27: sent- warm lead | AJ27: 25-03-2026 | AP27: GREEN | AQ27: Dear Jami, I'm reaching out from Pocket FM regarding the Seattle Sockeyes Hockey series. We believe this series has strong potential for adaptation into serialized audio, a rapidly growing format structurally distinct from traditional audiobooks. We'd like to propose a partnership that includes a License Fee of $1,000 and 12% share of Revenue, details on the full offer are below. We understand many authors have granted exclusive audiobook rights (often to Audible). We are not seeking audiobook rights. Instead, we license serialized audio series adaptation rights, which are closer in nature to a TV dramatization, but in audio form, than to a traditional narrated audiobook. Rather than recording the manuscript verbatim, we create a scripted, episodic adaptation featuring dual-cast or full-cast performances, cinematic sound design, and structured cliffhanger arcs. Episodes run ~10 minutes and are released serially, with progression-based monetization. This format functions as an incremental revenue stream alongside print, ebook, KU, and audiobook sales, not in competition with them. Given the layered world-building and sustained narrative momentum in Seattle Sockeyes Hockey, we see strong alignment with this dramatized serialized format. Pocket FM is the world's largest dedicated audio series platform, trusted by leading publishers and IP holders including Naver, Kakao, Blackstone, Recorded Books, Aethon, and China Literature. Our catalog includes globally recognized titles such as Solo Leveling, The Primal Hunter, and Omniscient Reader's Viewpoint. In the past 12 months, we've delivered: 120 billion minutes of listening 18 million monthly active users $342M in revenue 200+ million global downloads Our app is rated 4.7 on the App Store and 4.5 on Google Play. Several titles have scaled meaningfully through this model, including: My Vampire System: 1B+ listens, $100M+ revenue Saving Nora: $42M revenue The Duke's Masked Bride: 641M plays The Alpha's Bride: 415M plays You can hear an example of our production quality here: https://pocketfm.com/show/ba2d9038fc3853c464c8be7a34a0576f26145106 We are proposing: License Fee: $1,000 Revenue Share: 12% of Revenue Exclusive serialized audio series adaptation rights (distinct from audiobook rights) English language (U.S./U.K.) 5-10 year term Full IP ownership retained by the author We are focused on long-term partnerships and would welcome discussion around additional titles within your catalog as well. If of interest, I'd be glad to schedule a brief call to discuss further. Best regards, Pulaksh Khimesara US Licensing & Commissioning Pocket FM
A28: P1 | B28: 70 | C28: Hawkeyes Hockey | D28: Kenna King | E28: 94.14 | F28: 9 | G28: Cocky Score | H28: Wrong Score | I28: 3.9 | J28: 20106 | K28: Tier 1 (>=20k) | L28: 0.1985 | M28: WEAK <30% | N28: Ice Hockey / Sports Romance | O28: Long Series | P28: After 2020 | Q28: Amazon Top 50 | R28: Amazon Top 50 | S28: Sports Romance (Paid) #22 | T28: 22 | U28: Needgap | V28: 1 | W28: $17,500 - $25,000 | X28: 15% | Y28: 15% - 22% | Z28: NEED CONTACT | AA28: Kenna King | AB28: Indie | AD28: FALSE | AG28: https://kennakingbooks.com/ | AH28: Website: https://kennakingbooks.com/ | AI28: =vlookup(C28,'Az working sheet Hockey Sports'!A:AT,45,0) | AP28: YELLOW | AS28: contact_form_url | AT28: https://kennakingbooks.com/pages/contact | AU28: Not Found | AV28: Contact page on official website. | Audit note: normalized row to validated contact state.
A29: P1 | B29: 65 | C29: Hockey Ever After | D29: Ashlyn Kane | E29: 53.76 | F29: 5 | G29: Winging It | H29: Textbook Defense | I29: 3.79 | J29: 7702 | K29: Tier 2 (>=5k) | L29: 0.1427 | M29: WEAK <30% | N29: Ice Hockey / Sports Romance | O29: Series | P29: After 2020 | Q29: Sports T100 | R29: Sports T100 | U29: Needgap | V29: 6 | W29: $5,000 - $7,500 | X29: 15% | Y29: 15% - 20% | Z29: NEED CONTACT | AA29: Ashlyn Kane | AB29: Indie | AD29: FALSE | AG29: http://ashlynkane.ca | AH29: Website: http://ashlynkane.ca | AI29: =vlookup(C29,'Az working sheet Hockey Sports'!A:AT,45,0) | AP29: YELLOW | AS29: contact_form_url | AT29: https://ashlynkane.ca/newsletter/ | AU29: Not Found | AV29: Newsletter signup; website contact form. No direct email. | Audit note: normalized row to validated contact state.
A30: P3 | B30: 38 | C30: Chatam House | D30: Arlene James | E30: 72.9 | F30: 9 | G30: Anna Meets Her Match | H30: The Doctor's Perfect Match | I30: 3.99 | J30: 202 | K30: Tier 3 (<5k) | L30: 0.5842 | M30: STRONG >=50% | N30: Ice Hockey / Sports Romance | O30: Long Series | P30: Before 2020 | U30: Needgap | V30: 9 | W30: Up to $1,000 | X30: 12% | Y30: 12% - 18% | Z30: READY (low ratings) | AA30: Silhouette Books | AB30: Big Pub | AC30: deararlenejames@gmail.com | AD30: TRUE | AG30: http://www.arlenejames.com | AH30: Email: deararlenejames@gmail.com | Website: http://www.arlenejames.com | AI30: =vlookup(C30,'Mail Merge'!B:J,9,0) | AJ30: 46207 | AP30: GREEN | AQ30: Dear Arlene, I'm reaching out from Pocket FM regarding the Chatam House series. We believe this series has strong potential for adaptation into serialized audio, a rapidly growing format structurally distinct from traditional audiobooks. We'd like to propose a partnership that includes a License Fee of $1,000 and 12% share of Revenue, details on the full offer are below. We understand many authors have granted exclusive audiobook rights (often to Audible). We are not seeking audiobook rights. Instead, we license serialized audio series adaptation rights, which are closer in nature to a TV dramatization, but in audio form, than to a traditional narrated audiobook. Rather than recording the manuscript verbatim, we create a scripted, episodic adaptation featuring dual-cast or full-cast performances, cinematic sound design, and structured cliffhanger arcs. Episodes run ~10 minutes and are released serially, with progression-based monetization. This format functions as an incremental revenue stream alongside print, ebook, KU, and audiobook sales, not in competition with them. Given the layered world-building and sustained narrative momentum in Chatam House, we see strong alignment with this dramatized serialized format. Pocket FM is the world's largest dedicated audio series platform, trusted by leading publishers and IP holders including Naver, Kakao, Blackstone, Recorded Books, Aethon, and China Literature. Our catalog includes globally recognized titles such as Solo Leveling, The Primal Hunter, and Omniscient Reader's Viewpoint. In the past 12 months, we've delivered: 120 billion minutes of listening 18 million monthly active users $342M in revenue 200+ million global downloads Our app is rated 4.7 on the App Store and 4.5 on Google Play. Several titles have scaled meaningfully through this model, including: My Vampire System: 1B+ listens, $100M+ revenue Saving Nora: $42M revenue The Duke's Masked Bride: 641M plays The Alpha's Bride: 415M plays You can hear an example of our production quality here: https://pocketfm.com/show/ba2d9038fc3853c464c8be7a34a0576f26145106 We are proposing: License Fee: $1,000 Revenue Share: 12% of Revenue Exclusive serialized audio series adaptation rights (distinct from audiobook rights) English language (U.S./U.K.) 5-10 year term Full IP ownership retained by the author We are focused on long-term partnerships and would welcome discussion around additional titles within your catalog as well. If of interest, I'd be glad to schedule a brief call to discuss further. Best regards, Pulaksh Khimesara US Licensing & Commissioning Pocket FM
A31: P1 | B31: 65 | C31: Fake Boyfriend | D31: Eden Finley | E31: 55.68 | F31: 6 | G31: Fake Out | H31: Final Play | I31: 3.97 | J31: 30668 | K31: Tier 1 (>=20k) | L31: 0.4603 | M31: MODERATE 30-50% | N31: Ice Hockey / Sports Romance | O31: Long Series | P31: Before 2020 | Q31: Amazon Top 100 | R31: Amazon Top 100 | U31: Needgap | V31: 2 | W31: $17,500 - $20,000 | X31: 15% | Y31: 15% - 22% | Z31: READY | AA31: Eden Finley | AB31: Self-Pub | AC31: assistant@edenfinley.com | AD31: TRUE | AF31: Contact form on official website | AG31: https://edenfinley.com/ | AH31: Email: assistant@edenfinley.com | Agent: Contact form on official website | Website: https://edenfinley.com/ | AI31: =vlookup(C31,'Az working sheet Hockey Sports'!A:AT,45,0) | AP31: YELLOW | AQ31: Dear Eden, I'm reaching out from Pocket FM regarding the Fake Boyfriend series. We believe this series has strong potential for adaptation into serialized audio, a rapidly growing format structurally distinct from traditional audiobooks. We'd like to propose a partnership that includes a License Fee of $20,000 and 15% share of Revenue, details on the full offer are below. We understand many authors have granted exclusive audiobook rights (often to Audible). We are not seeking audiobook rights. Instead, we license serialized audio series adaptation rights, which are closer in nature to a TV dramatization, but in audio form, than to a traditional narrated audiobook. Rather than recording the manuscript verbatim, we create a scripted, episodic adaptation featuring dual-cast or full-cast performances, cinematic sound design, and structured cliffhanger arcs. Episodes run ~10 minutes and are released serially, with progression-based monetization. This format functions as an incremental revenue stream alongside print, ebook, KU, and audiobook sales, not in competition with them. Given the layered world-building and sustained narrative momentum in Fake Boyfriend, we see strong alignment with this dramatized serialized format. Pocket FM is the world's largest dedicated audio series platform, trusted by leading publishers and IP holders including Naver, Kakao, Blackstone, Recorded Books, Aethon, and China Literature. Our catalog includes globally recognized titles such as Solo Leveling, The Primal Hunter, and Omniscient Reader's Viewpoint. In the past 12 months, we've delivered: 120 billion minutes of listening 18 million monthly active users $342M in revenue 200+ million global downloads Our app is rated 4.7 on the App Store and 4.5 on Google Play. Several titles have scaled meaningfully through this model, including: My Vampire System: 1B+ listens, $100M+ revenue Saving Nora: $42M revenue The Duke's Masked Bride: 641M plays The Alpha's Bride: 415M plays You can hear an example of our production quality here: https://pocketfm.com/show/ba2d9038fc3853c464c8be7a34a0576f26145106 We are proposing: License Fee: $20,000 Revenue Share: 15% of Revenue Exclusive serialized audio series adaptation rights (distinct from audiobook rights) English language (U.S./U.K.) 5-10 year term Full IP ownership retained by the author We are focused on long-term partnerships and would welcome discussion around additional titles within your catalog as well. If of interest, I'd be glad to schedule a brief call to discuss further. Best regards, Pulaksh Khimesara US Licensing & Commissioning Pocket FM | AV31: NOTE: Already contacted Eden Finley for: Puckboys, CU Hockey
A32: P1 | B32: 60 | C32: Assassins | D32: Toni Aleo | E32: 131.22 | F32: 8 | G32: Taking Shots | H32: The Assassins Series | I32: 3.9 | J32: 23448 | K32: Tier 1 (>=20k) | L32: 0.4425 | M32: MODERATE 30-50% | N32: Ice Hockey / Sports Romance | O32: Long Series | P32: Before 2020 | U32: Needgap | V32: 1 | W32: $17,500 - $25,000 | X32: 15% | Y32: 15% - 22% | Z32: READY | AA32: Aleo Publishing | AB32: Self-Pub | AC32: toni@tonialeo.com | AD32: TRUE | AG32: https://tonialeo.com/ | AH32: Email: toni@tonialeo.com | Website: https://tonialeo.com/ | AI32: sent | AJ32: 46177 | AP32: GREEN | AQ32: Dear Toni, I'm reaching out from Pocket FM regarding the Assassins series. We believe this series has strong potential for adaptation into serialized audio, a rapidly growing format structurally distinct from traditional audiobooks. We'd like to propose a partnership that includes a License Fee of $25,000 and 15% share of Revenue, details on the full offer are below. We understand many authors have granted exclusive audiobook rights (often to Audible). We are not seeking audiobook rights. Instead, we license serialized audio series adaptation rights, which are closer in nature to a TV dramatization, but in audio form, than to a traditional narrated audiobook. Rather than recording the manuscript verbatim, we create a scripted, episodic adaptation featuring dual-cast or full-cast performances, cinematic sound design, and structured cliffhanger arcs. Episodes run ~10 minutes and are released serially, with progression-based monetization. This format functions as an incremental revenue stream alongside print, ebook, KU, and audiobook sales, not in competition with them. Given the layered world-building and sustained narrative momentum in Assassins, we see strong alignment with this dramatized serialized format. Pocket FM is the world's largest dedicated audio series platform, trusted by leading publishers and IP holders including Naver, Kakao, Blackstone, Recorded Books, Aethon, and China Literature. Our catalog includes globally recognized titles such as Solo Leveling, The Primal Hunter, and Omniscient Reader's Viewpoint. In the past 12 months, we've delivered: 120 billion minutes of listening 18 million monthly active users $342M in revenue 200+ million global downloads Our app is rated 4.7 on the App Store and 4.5 on Google Play. Several titles have scaled meaningfully through this model, including: My Vampire System: 1B+ listens, $100M+ revenue Saving Nora: $42M revenue The Duke's Masked Bride: 641M plays The Alpha's Bride: 415M plays You can hear an example of our production quality here: https://pocketfm.com/show/ba2d9038fc3853c464c8be7a34a0576f26145106 We are proposing: License Fee: $25,000 Revenue Share: 15% of Revenue Exclusive serialized audio series adaptation rights (distinct from audiobook rights) English language (U.S./U.K.) 5-10 year term Full IP ownership retained by the author We are focused on long-term partnerships and would welcome discussion around additional titles within your catalog as well. If of interest, I'd be glad to schedule a brief call to discuss further. Best regards, Pulaksh Khimesara US Licensing & Commissioning Pocket FM | AV32: NOTE: Already contacted Toni Aleo for: Nashville Assassins
A33: P1 | B33: 65 | C33: Slater Brothers | D33: L.A. Casey | E33: 117 | F33: 7 | G33: Dominic | H33: LOVE. Un nuovo destino - Un incredibile incontro - Un pensiero infinito | I33: 3.98 | J33: 27675 | K33: Tier 1 (>=20k) | L33: 0.0359 | M33: WEAK <30% | N33: Ice Hockey / Sports Romance | O33: Long Series | P33: Before 2020 | U33: Needgap | V33: 1 | W33: $17,500 - $25,000 | X33: 15% | Y33: 15% - 22% | Z33: NEED CONTACT | AA33: KM Publishing | AB33: Self-Pub | AD33: FALSE | AF33: Mark Gottlieb, Trident Media Group | AG33: http://lacaseyauthor.com/ | AH33: Agent: Mark Gottlieb, Trident Media Group | Website: http://lacaseyauthor.com/ | AI33: =vlookup(C33,'Az working sheet Hockey Sports'!A:AT,45,0) | AP33: YELLOW | AU33: Not Found
A34: P3 | B34: 45 | C34: Hot Ice | D34: Lily Harlem | E34: 44.7 | F34: 8 | G34: Hired | H34: Pucking The Team | I34: 3.63 | J34: 1688 | K34: Tier 3 (<5k) | L34: 0.0326 | M34: WEAK <30% | N34: Ice Hockey / Sports Romance | O34: Long Series | P34: Before 2020 | Q34: Amazon Top 10 | R34: Amazon Top 10 | U34: Needgap | V34: 9 | W34: Up to $1,000 | X34: 12% | Y34: 12% - 18% | Z34: READY (low ratings) | AA34: Harlem Nights Publishing | AB34: Self-Pub | AC34: lily@lilyharlem.com | AD34: TRUE | AG34: http://www.lilyharlem.com/ | AH34: Email: lily@lilyharlem.com | Website: http://www.lilyharlem.com/ | AI34: =vlookup(C34,'Mail Merge'!B:J,9,0) | AJ34: 46207 | AP34: GREEN | AQ34: Dear Lily, I'm reaching out from Pocket FM regarding the Hot Ice series. We believe this series has strong potential for adaptation into serialized audio, a rapidly growing format structurally distinct from traditional audiobooks. We'd like to propose a partnership that includes a License Fee of $1,000 and 12% share of Revenue, details on the full offer are below. We understand many authors have granted exclusive audiobook rights (often to Audible). We are not seeking audiobook rights. Instead, we license serialized audio series adaptation rights, which are closer in nature to a TV dramatization, but in audio form, than to a traditional narrated audiobook. Rather than recording the manuscript verbatim, we create a scripted, episodic adaptation featuring dual-cast or full-cast performances, cinematic sound design, and structured cliffhanger arcs. Episodes run ~10 minutes and are released serially, with progression-based monetization. This format functions as an incremental revenue stream alongside print, ebook, KU, and audiobook sales, not in competition with them. Given the layered world-building and sustained narrative momentum in Hot Ice, we see strong alignment with this dramatized serialized format. Pocket FM is the world's largest dedicated audio series platform, trusted by leading publishers and IP holders including Naver, Kakao, Blackstone, Recorded Books, Aethon, and China Literature. Our catalog includes globally recognized titles such as Solo Leveling, The Primal Hunter, and Omniscient Reader's Viewpoint. In the past 12 months, we've delivered: 120 billion minutes of listening 18 million monthly active users $342M in revenue 200+ million global downloads Our app is rated 4.7 on the App Store and 4.5 on Google Play. Several titles have scaled meaningfully through this model, including: My Vampire System: 1B+ listens, $100M+ revenue Saving Nora: $42M revenue The Duke's Masked Bride: 641M plays The Alpha's Bride: 415M plays You can hear an example of our production quality here: https://pocketfm.com/show/ba2d9038fc3853c464c8be7a34a0576f26145106 We are proposing: License Fee: $1,000 Revenue Share: 12% of Revenue Exclusive serialized audio series adaptation rights (distinct from audiobook rights) English language (U.S./U.K.) 5-10 year term Full IP ownership retained by the author We are focused on long-term partnerships and would welcome discussion around additional titles within your catalog as well. If of interest, I'd be glad to schedule a brief call to discuss further. Best regards, Pulaksh Khimesara US Licensing & Commissioning Pocket FM
A35: P3 | B35: 43 | C35: Slayers Hockey | D35: Mira Lyn Kelly | E35: 57.45 | F35: 8 | G35: Dirty Secret | H35: Dirty Flirt | I35: 3.99 | J35: 8606 | K35: Tier 2 (>=5k) | L35: 0.1488 | M35: WEAK <30% | N35: Ice Hockey / Sports Romance | O35: Long Series | P35: Before 2020 | U35: Needgap | V35: 6 | W35: $5,000 - $7,500 | X35: 15% | Y35: 15% - 20% | Z35: READY | AA35: Mira Lyn Kelly | AB35: Self-Pub | AC35: mira@miralynkelly.com | AD35: TRUE | AF35: Nicole Resciniti, The Seymour Agency | AG35: https://www.miralynkelly.com | AH35: Email: mira@miralynkelly.com | Agent: Nicole Resciniti, The Seymour Agency | Website: https://www.miralynkelly.com | AI35: =vlookup(C35,'Mail Merge'!B:J,9,0) | AJ35: 46207 | AP35: GREEN | AQ35: Dear Mira, I'm reaching out from Pocket FM regarding the Slayers Hockey series. We believe this series has strong potential for adaptation into serialized audio, a rapidly growing format structurally distinct from traditional audiobooks. We'd like to propose a partnership that includes a License Fee of $7,500 and 15% share of Revenue, details on the full offer are below. We understand many authors have granted exclusive audiobook rights (often to Audible). We are not seeking audiobook rights. Instead, we license serialized audio series adaptation rights, which are closer in nature to a TV dramatization, but in audio form, than to a traditional narrated audiobook. Rather than recording the manuscript verbatim, we create a scripted, episodic adaptation featuring dual-cast or full-cast performances, cinematic sound design, and structured cliffhanger arcs. Episodes run ~10 minutes and are released serially, with progression-based monetization. This format functions as an incremental revenue stream alongside print, ebook, KU, and audiobook sales, not in competition with them. Given the layered world-building and sustained narrative momentum in Slayers Hockey, we see strong alignment with this dramatized serialized format. Pocket FM is the world's largest dedicated audio series platform, trusted by leading publishers and IP holders including Naver, Kakao, Blackstone, Recorded Books, Aethon, and China Literature. Our catalog includes globally recognized titles such as Solo Leveling, The Primal Hunter, and Omniscient Reader's Viewpoint. In the past 12 months, we've delivered: 120 billion minutes of listening 18 million monthly active users $342M in revenue 200+ million global downloads Our app is rated 4.7 on the App Store and 4.5 on Google Play. Several titles have scaled meaningfully through this model, including: My Vampire System: 1B+ listens, $100M+ revenue Saving Nora: $42M revenue The Duke's Masked Bride: 641M plays The Alpha's Bride: 415M plays You can hear an example of our production quality here: https://pocketfm.com/show/ba2d9038fc3853c464c8be7a34a0576f26145106 We are proposing: License Fee: $7,500 Revenue Share: 15% of Revenue Exclusive serialized audio series adaptation rights (distinct from audiobook rights) English language (U.S./U.K.) 5-10 year term Full IP ownership retained by the author We are focused on long-term partnerships and would welcome discussion around additional titles within your catalog as well. If of interest, I'd be glad to schedule a brief call to discuss further. Best regards, Pulaksh Khimesara US Licensing & Commissioning Pocket FM
A36: P1 | B36: 63 | C36: Portland Storm | D36: Catherine Gayle | E36: 190.29 | F36: 8 | G36: Breakaway | H36: Double Major | I36: 3.97 | J36: 6323 | K36: Tier 2 (>=5k) | L36: 0.1977 | M36: WEAK <30% | N36: Ice Hockey / Sports Romance | O36: Long Series | P36: Before 2020 | Q36: Sports Top 50 | R36: Sports Top 50 | U36: Needgap | V36: 5 | W36: $12,500 - $17,500 | X36: 15% | Y36: 15% - 20% | Z36: NEED CONTACT | AA36: Catherine Gayle | AB36: Self-Pub | AD36: FALSE | AG36: https://catherinegayle.com | AH36: Website: https://catherinegayle.com | AI36: =vlookup(C36,'Az working sheet Hockey Sports'!A:AT,45,0) | AP36: YELLOW | AU36: Not Found
A37: P1 | B37: 63 | C37: The Rookie Hawkeyes | D37: Kenna King | E37: 33.84 | F37: 8 | G37: Match Penalty | H37: Final Shot | I37: 3.88 | J37: 5786 | K37: Tier 2 (>=5k) | M37: WEAK <30% | N37: Ice Hockey / Sports Romance | O37: Long Series | P37: After 2020 | S37: Sports Romance (Paid) #22 | T37: 22 | U37: Needgap | V37: 10 | W37: No MG | X37: 12% | Y37: 12% - 18% | Z37: BELOW LENGTH THRESHOLD | AA37: Kenna King | AB37: Self-Pub | AD37: FALSE | AG37: https://kennakingbooks.com/ | AH37: Website: https://kennakingbooks.com/ | AI37: =vlookup(C37,'Az working sheet Hockey Sports'!A:AT,45,0) | AP37: YELLOW | AS37: contact_form_url | AT37: https://kennakingbooks.com/pages/contact | AU37: Not Found | AV37: Contact page on official website. | Audit note: normalized row to validated contact state.
A38: P3 | B38: 30 | C38: Aces Hockey | D38: Kelly Jamieson | E38: 62.73 | F38: 8 | G38: Major Misconduct | H38: Game On | I38: 3.74 | J38: 3480 | K38: Tier 3 (<5k) | L38: 0.3575 | M38: MODERATE 30-50% | N38: Ice Hockey / Sports Romance | O38: Long Series | P38: Before 2020 | U38: Needgap | V38: 9 | W38: Up to $1,000 | X38: 12% | Y38: 12% - 18% | Z38: READY | AA38: Loveswept | AB38: Big Pub | AC38: info@kellyjamieson.com | AD38: TRUE | AF38: Contact form on official website | AG38: https://kellyjamieson.com | AH38: Email: info@kellyjamieson.com | Agent: Contact form on official website | Website: https://kellyjamieson.com | AI38: =vlookup(C38,'Mail Merge'!B:J,9,0) | AJ38: 46207 | AP38: GREEN | AQ38: Dear Kelly, I'm reaching out from Pocket FM regarding the Aces Hockey series. We believe this series has strong potential for adaptation into serialized audio, a rapidly growing format structurally distinct from traditional audiobooks. We'd like to propose a partnership that includes a License Fee of $1,000 and 12% share of Revenue, details on the full offer are below. We understand many authors have granted exclusive audiobook rights (often to Audible). We are not seeking audiobook rights. Instead, we license serialized audio series adaptation rights, which are closer in nature to a TV dramatization, but in audio form, than to a traditional narrated audiobook. Rather than recording the manuscript verbatim, we create a scripted, episodic adaptation featuring dual-cast or full-cast performances, cinematic sound design, and structured cliffhanger arcs. Episodes run ~10 minutes and are released serially, with progression-based monetization. This format functions as an incremental revenue stream alongside print, ebook, KU, and audiobook sales, not in competition with them. Given the layered world-building and sustained narrative momentum in Aces Hockey, we see strong alignment with this dramatized serialized format. Pocket FM is the world's largest dedicated audio series platform, trusted by leading publishers and IP holders including Naver, Kakao, Blackstone, Recorded Books, Aethon, and China Literature. Our catalog includes globally recognized titles such as Solo Leveling, The Primal Hunter, and Omniscient Reader's Viewpoint. In the past 12 months, we've delivered: 120 billion minutes of listening 18 million monthly active users $342M in revenue 200+ million global downloads Our app is rated 4.7 on the App Store and 4.5 on Google Play. Several titles have scaled meaningfully through this model, including: My Vampire System: 1B+ listens, $100M+ revenue Saving Nora: $42M revenue The Duke's Masked Bride: 641M plays The Alpha's Bride: 415M plays You can hear an example of our production quality here: https://pocketfm.com/show/ba2d9038fc3853c464c8be7a34a0576f26145106 We are proposing: License Fee: $1,000 Revenue Share: 12% of Revenue Exclusive serialized audio series adaptation rights (distinct from audiobook rights) English language (U.S./U.K.) 5-10 year term Full IP ownership retained by the author We are focused on long-term partnerships and would welcome discussion around additional titles within your catalog as well. If of interest, I'd be glad to schedule a brief call to discuss further. Best regards, Pulaksh Khimesara US Licensing & Commissioning Pocket FM | AV38: NOTE: Already contacted Kelly Jamieson for: Heller Brothers Hockey
A39: P5 | B39: 75 | C39: Millennium | D39: Stieg Larsson | E39: 15.09 | F39: 8 | G39: The Girl With the Dragon Tattoo | H39: The Girl with Ice in Her Veins | I39: 4.26 | J39: 987947 | K39: Tier 1 (>=20k) | L39: 1 | M39: STRONG >=50% | N39: Ice Hockey / Sports Romance | O39: Long Series | P39: Before 2020 | U39: Needgap | V39: 10 | W39: No MG | X39: 12% | Y39: 12% - 18% | Z39: BELOW LENGTH THRESHOLD | AA39: Vintage Books | AB39: Big Pub | AD39: TRUE | AF39: Magdalena Hedlund, Hedlund Literary Agency | AG39: http://www.denisemina.co.uk/ | AH39: Email: jonw@rcwlitagency.com | Agent email: hello@stieglarsson.com | Agent: Magdalena Hedlund, Hedlund Literary Agency | Website: http://www.denisemina.co.uk/ | AI39: =vlookup(C39,'Mail Merge'!B:J,9,0) | AJ39: 46207 | AP39: GREEN | AQ39: Dear Stieg, I'm reaching out from Pocket FM regarding the Millennium series. We believe this series has strong potential for adaptation into serialized audio, a rapidly growing format structurally distinct from traditional audiobooks. We'd like to propose a partnership that includes a License Fee of Revenue Share Only and 12% share of Revenue, details on the full offer are below. We understand many authors have granted exclusive audiobook rights (often to Audible). We are not seeking audiobook rights. Instead, we license serialized audio series adaptation rights, which are closer in nature to a TV dramatization, but in audio form, than to a traditional narrated audiobook. Rather than recording the manuscript verbatim, we create a scripted, episodic adaptation featuring dual-cast or full-cast performances, cinematic sound design, and structured cliffhanger arcs. Episodes run ~10 minutes and are released serially, with progression-based monetization. This format functions as an incremental revenue stream alongside print, ebook, KU, and audiobook sales, not in competition with them. Given the layered world-building and sustained narrative momentum in Millennium, we see strong alignment with this dramatized serialized format. Pocket FM is the world's largest dedicated audio series platform, trusted by leading publishers and IP holders including Naver, Kakao, Blackstone, Recorded Books, Aethon, and China Literature. Our catalog includes globally recognized titles such as Solo Leveling, The Primal Hunter, and Omniscient Reader's Viewpoint. In the past 12 months, we've delivered: 120 billion minutes of listening 18 million monthly active users $342M in revenue 200+ million global downloads Our app is rated 4.7 on the App Store and 4.5 on Google Play. Several titles have scaled meaningfully through this model, including: My Vampire System: 1B+ listens, $100M+ revenue Saving Nora: $42M revenue The Duke's Masked Bride: 641M plays The Alpha's Bride: 415M plays You can hear an example of our production quality here: https://pocketfm.com/show/ba2d9038fc3853c464c8be7a34a0576f26145106 We are proposing: License Fee: Revenue Share Only Revenue Share: 12% of Revenue Exclusive serialized audio series adaptation rights (distinct from audiobook rights) English language (U.S./U.K.) 5-10 year term Full IP ownership retained by the author We are focused on long-term partnerships and would welcome discussion around additional titles within your catalog as well. If of interest, I'd be glad to schedule a brief call to discuss further. Best regards, Pulaksh Khimesara US Licensing & Commissioning Pocket FM | AS39: author_email | AT39: https://stieglarsson.com/contact | AU39: High | AV39: Audit note: normalized row to validated contact state.
A40: P1 | B40: 60 | C40: Underground Kings | D40: Aurora Rose Reynolds | E40: 67.83 | F40: 5 | G40: Assumption LAST: Alpha URL: https://www.goodreads.com/series/132400-underground-kings | H40: Alpha URL: https://www.goodreads.com/series/132400-underground-kings | I40: 4.13 | J40: 21449 | K40: Tier 1 (>=20k) | M40: DATA_SCALE_MISMATCH | N40: Ice Hockey / Sports Romance | O40: Long Series | P40: Before 2020 | U40: Needgap | V40: 2 | W40: $17,500 - $20,000 | X40: 15% | Y40: 15% - 22% | Z40: NEED CONTACT | AA40: Aurora Rose Reynolds | AB40: Self-Pub | AD40: FALSE | AG40: https://aurorarosereynolds.com | AH40: Website: https://aurorarosereynolds.com | AI40: =vlookup(C40,'Az working sheet Hockey Sports'!A:AT,45,0) | AP40: YELLOW | AS40: contact_form_url | AT40: https://aurorarosereynolds.com/books/ | AU40: Not Found | AV40: Official website with contact. No direct email. | Audit note: normalized row to validated contact state.
A41: P1 | B41: 60 | C41: Standalone | D41: Flora Ferrari | E41: 75.15 | F41: 1 | G41: Hockey Obsession | H41: Hockey Obsession | I41: 3.82 | J41: 48650 | K41: Tier 1 (>=20k) | M41: WEAK <30% | N41: Ice Hockey / Sports Romance | O41: Standalone | P41: After 2020 | U41: Needgap | V41: 2 | W41: $17,500 - $20,000 | X41: 15% | Y41: 15% - 22% | Z41: NEED CONTACT | AA41: Flora Ferrari LLC | AB41: Self-Pub | AC41: jferrariadler@aevitascreative.com | AD41: FALSE | AE41: jferrariadler@aevitascreative.com | AF41: Jenni Ferrari-Adler Agent_Email: Website: None found. EMAIL: NONE | AG41: https://floraferrari.com | AH41: Website: https://floraferrari.com | AI41: =vlookup(C41,'Az working sheet Hockey Sports'!A:AT,45,0) | AP41: YELLOW | AS41: contact_form_url | AT41: https://floraferraribooks.com/ | AU41: Not Found | AV41: Official website; mailing list. No direct email. | Audit note: normalized row to validated contact state.
A42: P1 | B42: 60 | C42: Playing Dirty (A Sports Romance) | D42: Jillian Liota | E42: 63 | F42: 6 | G42: Intercepted | H42: Hat Trick | I42: 4.15 | J42: 3500 | K42: Tier 3 (<5k) | L42: 0.3429 | M42: MODERATE 30-50% | N42: Ice Hockey / Sports Romance | O42: Long Series | P42: After 2020 | Q42: Amazon Top 100 | R42: Amazon Top 100 | U42: Needgap | V42: 9 | W42: Up to $1,000 | X42: 12% | Y42: 12% - 18% | Z42: READY | AA42: Jillian Liota | AB42: Self-Pub | AC42: jillianliota@gmail.com | AD42: TRUE | AE42: jillianliota@gmail.com | AG42: http://www.jillianliota.com | AH42: Email: jillianliota@gmail.com | Agent email: jillianliota@gmail.com | Website: http://www.jillianliota.com | AI42: =vlookup(C42,'Az working sheet Hockey Sports'!A:AT,45,0) | AP42: RED | AQ42: Dear Jillian, I'm reaching out from Pocket FM regarding the Playing Dirty (A Sports Romance) series. We believe this series has strong potential for adaptation into serialized audio, a rapidly growing format structurally distinct from traditional audiobooks. We'd like to propose a partnership that includes a License Fee of $1,000 and 12% share of Revenue, details on the full offer are below. We understand many authors have granted exclusive audiobook rights (often to Audible). We are not seeking audiobook rights. Instead, we license serialized audio series adaptation rights, which are closer in nature to a TV dramatization, but in audio form, than to a traditional narrated audiobook. Rather than recording the manuscript verbatim, we create a scripted, episodic adaptation featuring dual-cast or full-cast performances, cinematic sound design, and structured cliffhanger arcs. Episodes run ~10 minutes and are released serially, with progression-based monetization. This format functions as an incremental revenue stream alongside print, ebook, KU, and audiobook sales, not in competition with them. Given the layered world-building and sustained narrative momentum in Playing Dirty (A Sports Romance), we see strong alignment with this dramatized serialized format. Pocket FM is the world's largest dedicated audio series platform, trusted by leading publishers and IP holders including Naver, Kakao, Blackstone, Recorded Books, Aethon, and China Literature. Our catalog includes globally recognized titles such as Solo Leveling, The Primal Hunter, and Omniscient Reader's Viewpoint. In the past 12 months, we've delivered: 120 billion minutes of listening 18 million monthly active users $342M in revenue 200+ million global downloads Our app is rated 4.7 on the App Store and 4.5 on Google Play. Several titles have scaled meaningfully through this model, including: My Vampire System: 1B+ listens, $100M+ revenue Saving Nora: $42M revenue The Duke's Masked Bride: 641M plays The Alpha's Bride: 415M plays You can hear an example of our production quality here: https://pocketfm.com/show/ba2d9038fc3853c464c8be7a34a0576f26145106 We are proposing: License Fee: $1,000 Revenue Share: 12% of Revenue Exclusive serialized audio series adaptation rights (distinct from audiobook rights) English language (U.S./U.K.) 5-10 year term Full IP ownership retained by the author We are focused on long-term partnerships and would welcome discussion around additional titles within your catalog as well. If of interest, I'd be glad to schedule a brief call to discuss further. Best regards, Pulaksh Khimesara US Licensing & Commissioning Pocket FM
A43: P1 | B43: 60 | C43: Campus Nights | D43: Rebecca Jenshak | E43: 38.04 | F43: 4 | G43: Secret Puck | H43: Wild Love | I43: 3.84 | J43: 14197 | K43: Tier 2 (>=5k) | L43: 0.5081 | M43: STRONG >=50% | N43: Ice Hockey / Sports Romance | O43: Series | P43: After 2020 | U43: Needgap | V43: 10 | W43: No MG | X43: 12% | Y43: 12% - 18% | Z43: BELOW LENGTH THRESHOLD | AA43: Rebecca Jenshak | AB43: Self-Pub | AD43: FALSE | AF43: Contact form on official website | AG43: https://rebeccajenshak.com | AH43: Agent: Contact form on official website | Website: https://rebeccajenshak.com | AI43: =vlookup(C43,'Az working sheet Hockey Sports'!A:AT,45,0) | AP43: YELLOW | AU43: Not Found | AV43: NOTE: Already contacted Rebecca Jenshak for: Wildcat Hockey | Already outreached for this author on: Wildcat Hockey
A44: P1 | B44: 60 | C44: Hockey Gods | D44: S. Massery | E44: 75.09 | F44: 5 | G44: Brutal Obsession | H44: Fierce Obsession | I44: 3.82 | J44: 48650 | K44: Tier 1 (>=20k) | M44: WEAK <30% | N44: Ice Hockey / Sports Romance | O44: Series | P44: After 2020 | U44: Needgap | V44: 2 | W44: $17,500 - $20,000 | X44: 15% | Y44: 15% - 22% | Z44: NEED CONTACT | AA44: S. Massery | AB44: Self-Pub | AD44: FALSE | AG44: https://smassery.com | AH44: Website: https://smassery.com | AI44: =vlookup(C44,'Az working sheet Hockey Sports'!A:AT,45,0) | AP44: YELLOW | AS44: contact_form_url | AT44: https://smassery.com/pages/contact | AU44: Not Found | AV44: Contact page on official website. | Audit note: normalized row to validated contact state.
A45: P5 | B45: 43 | C45: Blairwood University | D45: Anna B. Doe | E45: 111.12 | F45: 8 | G45: Kiss to Conquer | H45: Kiss Me Tenderly | I45: 3.81 | J45: 5094 | K45: Tier 2 (>=5k) | L45: 0.2183 | M45: WEAK <30% | N45: Ice Hockey / Sports Romance | O45: Long Series | P45: Before 2020 | U45: Needgap | V45: 5 | W45: 4000 | X45: 0.15 | Y45: 15% - 20% | Z45: READY | AA45: Wild heart publishing d.o.o. | AB45: Indie | AC45: annabdoe@gmail.com | AD45: TRUE | AE45: taj@ldlainc.com, queries@ldlainc.com | AF45: Taj McCoy | AG45: https://www.annabdoe.com | AH45: Email: annabdoe@gmail.com | Website: https://www.annabdoe.com | AI45: sent to Taj and Anna | AJ45: 46207 | AP45: GREEN | AQ45: Dear Anna, I'm reaching out from Pocket FM regarding the Blairwood University series. We believe this series has strong potential for adaptation into serialized audio, a rapidly growing format structurally distinct from traditional audiobooks. We'd like to propose a partnership that includes a License Fee of $17,500 and 15% share of Revenue, details on the full offer are below. We understand many authors have granted exclusive audiobook rights (often to Audible). We are not seeking audiobook rights. Instead, we license serialized audio series adaptation rights, which are closer in nature to a TV dramatization, but in audio form, than to a traditional narrated audiobook. Rather than recording the manuscript verbatim, we create a scripted, episodic adaptation featuring dual-cast or full-cast performances, cinematic sound design, and structured cliffhanger arcs. Episodes run ~10 minutes and are released serially, with progression-based monetization. This format functions as an incremental revenue stream alongside print, ebook, KU, and audiobook sales, not in competition with them. Given the layered world-building and sustained narrative momentum in Blairwood University, we see strong alignment with this dramatized serialized format. Pocket FM is the world's largest dedicated audio series platform, trusted by leading publishers and IP holders including Naver, Kakao, Blackstone, Recorded Books, Aethon, and China Literature. Our catalog includes globally recognized titles such as Solo Leveling, The Primal Hunter, and Omniscient Reader's Viewpoint. In the past 12 months, we've delivered: 120 billion minutes of listening 18 million monthly active users $342M in revenue 200+ million global downloads Our app is rated 4.7 on the App Store and 4.5 on Google Play. Several titles have scaled meaningfully through this model, including: My Vampire System: 1B+ listens, $100M+ revenue Saving Nora: $42M revenue The Duke's Masked Bride: 641M plays The Alpha's Bride: 415M plays You can hear an example of our production quality here: https://pocketfm.com/show/ba2d9038fc3853c464c8be7a34a0576f26145106 We are proposing: License Fee: $17,500 Revenue Share: 15% of Revenue Exclusive serialized audio series adaptation rights (distinct from audiobook rights) English language (U.S./U.K.) 5-10 year term Full IP ownership retained by the author We are focused on long-term partnerships and would welcome discussion around additional titles within your catalog as well. If of interest, I'd be glad to schedule a brief call to discuss further. Best regards, Pulaksh Khimesara US Licensing & Commissioning Pocket FM
A46: P0 | B46: 70 | C46: Game Changers | D46: Rachel Reid | E46: 76.95 | F46: 7 | G46: Game Changer | H46: Unrivaled | I46: 3.82 | J46: 112142 | K46: Tier 1 (>=20k) | M46: WEAK <30% | N46: Ice Hockey / Sports Romance | O46: Long Series | P46: Before 2020 | S46: Sports Romance (Paid) #16 | T46: 16 | U46: Needgap | V46: 2 | W46: 15000 | X46: 15% | Y46: 15% - 22% | Z46: READY | AA46: Carina Press | AB46: Indie | AC46: kdwyer@leoprny.com | AD46: TRUE | AE46: deidre.knight@knightagency.net | AF46: Deidre Knight | AG46: http://www.rachelreidwrites.com | AH46: Email: kdwyer@leoprny.com | Agent: Deidre Knight | Website: http://www.rachelreidwrites.com | AI46: sent to Deidre (agent) | AJ46: 46177 | AP46: GREEN | AQ46: Dear Rachel, I'm reaching out from Pocket FM regarding the Game Changers series. We believe this series has strong potential for adaptation into serialized audio, a rapidly growing format structurally distinct from traditional audiobooks. We'd like to propose a partnership that includes a License Fee of $20,000 and 15% share of Revenue, details on the full offer are below. We understand many authors have granted exclusive audiobook rights (often to Audible). We are not seeking audiobook rights. Instead, we license serialized audio series adaptation rights, which are closer in nature to a TV dramatization, but in audio form, than to a traditional narrated audiobook. Rather than recording the manuscript verbatim, we create a scripted, episodic adaptation featuring dual-cast or full-cast performances, cinematic sound design, and structured cliffhanger arcs. Episodes run ~10 minutes and are released serially, with progression-based monetization. This format functions as an incremental revenue stream alongside print, ebook, KU, and audiobook sales, not in competition with them. Given the layered world-building and sustained narrative momentum in Game Changers, we see strong alignment with this dramatized serialized format. Pocket FM is the world's largest dedicated audio series platform, trusted by leading publishers and IP holders including Naver, Kakao, Blackstone, Recorded Books, Aethon, and China Literature. Our catalog includes globally recognized titles such as Solo Leveling, The Primal Hunter, and Omniscient Reader's Viewpoint. In the past 12 months, we've delivered: 120 billion minutes of listening 18 million monthly active users $342M in revenue 200+ million global downloads Our app is rated 4.7 on the App Store and 4.5 on Google Play. Several titles have scaled meaningfully through this model, including: My Vampire System: 1B+ listens, $100M+ revenue Saving Nora: $42M revenue The Duke's Masked Bride: 641M plays The Alpha's Bride: 415M plays You can hear an example of our production quality here: https://pocketfm.com/show/ba2d9038fc3853c464c8be7a34a0576f26145106 We are proposing: License Fee: $20,000 Revenue Share: 15% of Revenue Exclusive serialized audio series adaptation rights (distinct from audiobook rights) English language (U.S./U.K.) 5-10 year term Full IP ownership retained by the author We are focused on long-term partnerships and would welcome discussion around additional titles within your catalog as well. If of interest, I'd be glad to schedule a brief call to discuss further. Best regards, Pulaksh Khimesara US Licensing & Commissioning Pocket FM
A47: P1 | B47: 58 | C47: Wildwood Society | D47: Andi Burns | E47: 94.14 | F47: 11 | G47: Boyfriend | H47: Goalkeeper | I47: 3.98 | J47: 7802 | K47: Tier 2 (>=5k) | L47: 0.009 | M47: WEAK <30% | N47: Ice Hockey / Sports Romance | O47: Long Series | P47: After 2020 | Q47: Amazon Top 50 | R47: Amazon Top 50 | U47: Needgap | V47: 5 | W47: $12,500 - $17,500 | X47: 15% | Y47: 15% - 20% | Z47: NEED CONTACT | AA47: Andi Burns | AB47: Self-Pub | AD47: FALSE | AG47: https://andiburnsauthor.com | AH47: Website: https://andiburnsauthor.com | AI47: =vlookup(C47,'Az working sheet Hockey Sports'!A:AT,45,0) | AP47: YELLOW | AS47: author_direct | AT47: https://roxienoir.com/ | AU47: Medium | AV47: ⚠️ DATA CORRECTION: 'Wildwood Society' is by ROXIE NOIR not Andi Burns. Verify attribution. Email is for Roxie Noir. | Audit note: normalized row to validated contact state.
A48: P1 | B48: 73 | C48: Love in Maple Falls | D48: Whitney Dineen | E48: 110.88 | F48: 7 | G48: Fake-Off with Fate LAST: The Icing on the Cake URL: UNKNOWN | H48: The Icing on the Cake URL: UNKNOWN | I48: 3.92 | J48: 876 | K48: Tier 3 (<5k) | L48: 0.6313 | M48: STRONG >=50% | N48: Ice Hockey / Sports Romance | O48: Long Series | P48: After 2020 | Q48: Hockey Top 100 | R48: Hockey Top 100 | U48: Needgap | V48: 9 | W48: Up to $1,000 | X48: 12% | Y48: 12% - 18% | Z48: READY (low ratings) | AA48: Becky Moore Author | AB48: Self-Pub | AC48: whitneydineenauthor@gmail.com | AD48: TRUE | AF48: Scott Schwimer, Esq | AH48: Email: whitneydineenauthor@gmail.com | Agent: Scott Schwimer, Esq | AI48: =vlookup(C48,'Az working sheet Hockey Sports'!A:AT,45,0) | AJ48: 25-03-2026 | AP48: GREEN | AQ48: Dear Whitney, I'm reaching out from Pocket FM regarding the Love in Maple Falls series. We believe this series has strong potential for adaptation into serialized audio, a rapidly growing format structurally distinct from traditional audiobooks. We'd like to propose a partnership that includes a License Fee of $1,000 and 12% share of Revenue, details on the full offer are below. We understand many authors have granted exclusive audiobook rights (often to Audible). We are not seeking audiobook rights. Instead, we license serialized audio series adaptation rights, which are closer in nature to a TV dramatization, but in audio form, than to a traditional narrated audiobook. Rather than recording the manuscript verbatim, we create a scripted, episodic adaptation featuring dual-cast or full-cast performances, cinematic sound design, and structured cliffhanger arcs. Episodes run ~10 minutes and are released serially, with progression-based monetization. This format functions as an incremental revenue stream alongside print, ebook, KU, and audiobook sales, not in competition with them. Given the layered world-building and sustained narrative momentum in Love in Maple Falls, we see strong alignment with this dramatized serialized format. Pocket FM is the world's largest dedicated audio series platform, trusted by leading publishers and IP holders including Naver, Kakao, Blackstone, Recorded Books, Aethon, and China Literature. Our catalog includes globally recognized titles such as Solo Leveling, The Primal Hunter, and Omniscient Reader's Viewpoint. In the past 12 months, we've delivered: 120 billion minutes of listening 18 million monthly active users $342M in revenue 200+ million global downloads Our app is rated 4.7 on the App Store and 4.5 on Google Play. Several titles have scaled meaningfully through this model, including: My Vampire System: 1B+ listens, $100M+ revenue Saving Nora: $42M revenue The Duke's Masked Bride: 641M plays The Alpha's Bride: 415M plays You can hear an example of our production quality here: https://pocketfm.com/show/ba2d9038fc3853c464c8be7a34a0576f26145106 We are proposing: License Fee: $1,000 Revenue Share: 12% of Revenue Exclusive serialized audio series adaptation rights (distinct from audiobook rights) English language (U.S./U.K.) 5-10 year term Full IP ownership retained by the author We are focused on long-term partnerships and would welcome discussion around additional titles within your catalog as well. If of interest, I'd be glad to schedule a brief call to discuss further. Best regards, Pulaksh Khimesara US Licensing & Commissioning Pocket FM
A49: P1 | B49: 58 | C49: Shots on Goal | D49: Kristen Hope Mazzola | E49: 40.68 | F49: 8 | G49: Hat Trick | H49: First Last Kiss | I49: 3.69 | J49: 9073 | K49: Tier 2 (>=5k) | L49: 0.0064 | M49: WEAK <30% | N49: Ice Hockey / Sports Romance | O49: Long Series | P49: Before 2020 | U49: Needgap | V49: 6 | W49: $5,000 - $7,500 | X49: 15% | Y49: 15% - 20% | Z49: NEED CONTACT | AB49: Indie | AD49: FALSE | AG49: https://www.kristenhopemazzola.com | AH49: Website: https://www.kristenhopemazzola.com | AI49: =vlookup(C49,'Az working sheet Hockey Sports'!A:AT,45,0) | AP49: YELLOW | AS49: contact_form_url | AT49: http://www.kristenhopemazzola.com/contact.html | AU49: Not Found | AV49: USA Today/WSJ bestselling author. Contact page on website. | Audit note: normalized row to validated contact state.
A50: P1 | C50: Real | D50: Katy Evans | E50: 65.1 | F50: 7 | G50: Real | H50: Racer | I50: 4.11 | J50: 114622 | K50: Tier 1 (>=20k) | L50: 0.0696 | M50: WEAK <30% | N50: Ice Hockey / Sports Romance | O50: Long Series | U50: Needgap | V50: 2 | W50: 15000 | X50: 15% | Y50: 15% - 22% | Z50: READY | AA50: Indie | AB50: Indie | AC50: katyevansauthor@gmail.com | AD50: TRUE | AF50: Amy Tannenbaum, Jane Rotrosen Agency | AG50: http://www.katyevans.net | AH50: Email: katyevansauthor@gmail.com | Agent: Amy Tannenbaum, Jane Rotrosen Agency | Website: http://www.katyevans.net | AI50: sent | AJ50: 46177 | AP50: GREEN | AQ50: Dear Katy, I'm reaching out from Pocket FM regarding the Real series. We believe this series has strong potential for adaptation into serialized audio, a rapidly growing format structurally distinct from traditional audiobooks. We'd like to propose a partnership that includes a License Fee of $20,000 and 15% share of Revenue, details on the full offer are below. We understand many authors have granted exclusive audiobook rights (often to Audible). We are not seeking audiobook rights. Instead, we license serialized audio series adaptation rights, which are closer in nature to a TV dramatization, but in audio form, than to a traditional narrated audiobook. Rather than recording the manuscript verbatim, we create a scripted, episodic adaptation featuring dual-cast or full-cast performances, cinematic sound design, and structured cliffhanger arcs. Episodes run ~10 minutes and are released serially, with progression-based monetization. This format functions as an incremental revenue stream alongside print, ebook, KU, and audiobook sales, not in competition with them. Given the layered world-building and sustained narrative momentum in Real, we see strong alignment with this dramatized serialized format. Pocket FM is the world's largest dedicated audio series platform, trusted by leading publishers and IP holders including Naver, Kakao, Blackstone, Recorded Books, Aethon, and China Literature. Our catalog includes globally recognized titles such as Solo Leveling, The Primal Hunter, and Omniscient Reader's Viewpoint. In the past 12 months, we've delivered: 120 billion minutes of listening 18 million monthly active users $342M in revenue 200+ million global downloads Our app is rated 4.7 on the App Store and 4.5 on Google Play. Several titles have scaled meaningfully through this model, including: My Vampire System: 1B+ listens, $100M+ revenue Saving Nora: $42M revenue The Duke's Masked Bride: 641M plays The Alpha's Bride: 415M plays You can hear an example of our production quality here: https://pocketfm.com/show/ba2d9038fc3853c464c8be7a34a0576f26145106 We are proposing: License Fee: $20,000 Revenue Share: 15% of Revenue Exclusive serialized audio series adaptation rights (distinct from audiobook rights) English language (U.S./U.K.) 5-10 year term Full IP ownership retained by the author We are focused on long-term partnerships and would welcome discussion around additional titles within your catalog as well. If of interest, I'd be glad to schedule a brief call to discuss further. Best regards, Pulaksh Khimesara US Licensing & Commissioning Pocket FM
A51: P2 | B51: 50 | C51: Western Wildcats Hockey | D51: Jennifer Sucevic | E51: 71.73 | F51: 7 | G51: Hate You Always | H51: Never Your Girl | I51: 3.72 | J51: 15264 | K51: Tier 2 (>=5k) | L51: 0.2282 | M51: WEAK <30% | N51: Ice Hockey / Sports Romance | O51: Long Series | P51: After 2020 | S51: Sports Romance (Paid) #28 | T51: 28 | U51: Needgap | V51: 6 | W51: 5000 | X51: 15% | Y51: 15% - 20% | Z51: READY | AA51: Jennifer Sucevic | AB51: Self-Pub | AC51: author@jennifersucevic.com | AD51: TRUE | AG51: https://www.jennifersucevic.com | AH51: Email: author@jennifersucevic.com | Website: https://www.jennifersucevic.com | AI51: sent to jennifer | AJ51: 46177 | AP51: GREEN | AQ51: Dear Jennifer, I'm reaching out from Pocket FM regarding the Western Wildcats Hockey series. We believe this series has strong potential for adaptation into serialized audio, a rapidly growing format structurally distinct from traditional audiobooks. We'd like to propose a partnership that includes a License Fee of $7,500 and 15% share of Revenue, details on the full offer are below. We understand many authors have granted exclusive audiobook rights (often to Audible). We are not seeking audiobook rights. Instead, we license serialized audio series adaptation rights, which are closer in nature to a TV dramatization, but in audio form, than to a traditional narrated audiobook. Rather than recording the manuscript verbatim, we create a scripted, episodic adaptation featuring dual-cast or full-cast performances, cinematic sound design, and structured cliffhanger arcs. Episodes run ~10 minutes and are released serially, with progression-based monetization. This format functions as an incremental revenue stream alongside print, ebook, KU, and audiobook sales, not in competition with them. Given the layered world-building and sustained narrative momentum in Western Wildcats Hockey, we see strong alignment with this dramatized serialized format. Pocket FM is the world's largest dedicated audio series platform, trusted by leading publishers and IP holders including Naver, Kakao, Blackstone, Recorded Books, Aethon, and China Literature. Our catalog includes globally recognized titles such as Solo Leveling, The Primal Hunter, and Omniscient Reader's Viewpoint. In the past 12 months, we've delivered: 120 billion minutes of listening 18 million monthly active users $342M in revenue 200+ million global downloads Our app is rated 4.7 on the App Store and 4.5 on Google Play. Several titles have scaled meaningfully through this model, including: My Vampire System: 1B+ listens, $100M+ revenue Saving Nora: $42M revenue The Duke's Masked Bride: 641M plays The Alpha's Bride: 415M plays You can hear an example of our production quality here: https://pocketfm.com/show/ba2d9038fc3853c464c8be7a34a0576f26145106 We are proposing: License Fee: $7,500 Revenue Share: 15% of Revenue Exclusive serialized audio series adaptation rights (distinct from audiobook rights) English language (U.S./U.K.) 5-10 year term Full IP ownership retained by the author We are focused on long-term partnerships and would welcome discussion around additional titles within your catalog as well. If of interest, I'd be glad to schedule a brief call to discuss further. Best regards, Pulaksh Khimesara US Licensing & Commissioning Pocket FM | AV51: NOTE: Already contacted Jennifer Sucevic for: Chicago Railers Hockey
A52: P2 | B52: 50 | C52: Hot Jocks | D52: Kendall Ryan | E52: 64.56 | F52: 7 | G52: Playing for Keeps | H52: Taking His Shot | I52: 3.72 | J52: 28674 | K52: Tier 1 (>=20k) | L52: 0.1966 | M52: WEAK <30% | N52: Ice Hockey / Sports Romance | O52: Long Series | P52: Before 2020 | U52: Needgap | V52: 2 | W52: 8000 | X52: 15% | Y52: 15% - 22% | Z52: READY | AA52: Kendall Ryan | AB52: Self-Pub | AC52: kendall@kendallryanbooks.com | AD52: TRUE | AF52: Jane Dystel | AG52: https://kendallryanbooks.com | AH52: Email: hello@plottwistmarketing.com | Agent: Jane Dystel | Website: https://kendallryanbooks.com | AI52: sent to kendall | AJ52: 46177 | AP52: GREEN | AQ52: Dear Kendall, I'm reaching out from Pocket FM regarding the Hot Jocks series. We believe this series has strong potential for adaptation into serialized audio, a rapidly growing format structurally distinct from traditional audiobooks. We'd like to propose a partnership that includes a License Fee of $20,000 and 15% share of Revenue, details on the full offer are below. We understand many authors have granted exclusive audiobook rights (often to Audible). We are not seeking audiobook rights. Instead, we license serialized audio series adaptation rights, which are closer in nature to a TV dramatization, but in audio form, than to a traditional narrated audiobook. Rather than recording the manuscript verbatim, we create a scripted, episodic adaptation featuring dual-cast or full-cast performances, cinematic sound design, and structured cliffhanger arcs. Episodes run ~10 minutes and are released serially, with progression-based monetization. This format functions as an incremental revenue stream alongside print, ebook, KU, and audiobook sales, not in competition with them. Given the layered world-building and sustained narrative momentum in Hot Jocks, we see strong alignment with this dramatized serialized format. Pocket FM is the world's largest dedicated audio series platform, trusted by leading publishers and IP holders including Naver, Kakao, Blackstone, Recorded Books, Aethon, and China Literature. Our catalog includes globally recognized titles such as Solo Leveling, The Primal Hunter, and Omniscient Reader's Viewpoint. In the past 12 months, we've delivered: 120 billion minutes of listening 18 million monthly active users $342M in revenue 200+ million global downloads Our app is rated 4.7 on the App Store and 4.5 on Google Play. Several titles have scaled meaningfully through this model, including: My Vampire System: 1B+ listens, $100M+ revenue Saving Nora: $42M revenue The Duke's Masked Bride: 641M plays The Alpha's Bride: 415M plays You can hear an example of our production quality here: https://pocketfm.com/show/ba2d9038fc3853c464c8be7a34a0576f26145106 We are proposing: License Fee: $20,000 Revenue Share: 15% of Revenue Exclusive serialized audio series adaptation rights (distinct from audiobook rights) English language (U.S./U.K.) 5-10 year term Full IP ownership retained by the author We are focused on long-term partnerships and would welcome discussion around additional titles within your catalog as well. If of interest, I'd be glad to schedule a brief call to discuss further. Best regards, Pulaksh Khimesara US Licensing & Commissioning Pocket FM
A53: P1 | B53: 53 | C53: Scoring Chances | D53: Avon Gale | E53: 32.85 | F53: 6 | G53: Save of the Game | H53: Coach's Challenge | I53: 4.11 | J53: 4093 | K53: Tier 3 (<5k) | L53: 1 | M53: STRONG >=50% | N53: Ice Hockey / Sports Romance | O53: Long Series | P53: Before 2020 | Q53: Amazon Top 50 | R53: Amazon Top 50 | U53: Needgap | V53: 10 | W53: No MG | X53: 12% | Y53: 12% - 18% | Z53: BELOW LENGTH THRESHOLD | AA53: Dreamspinner Press (Inferred) | AB53: Self-Pub | AD53: FALSE | AF53: Courtney Miller-Callihan, Handspun Literary Agency | AG53: https://www.casinosjungle.com/ | AH53: Agent: Courtney Miller-Callihan, Handspun Literary Agency | Website: https://www.casinosjungle.com/ | AI53: =vlookup(C53,'Az working sheet Hockey Sports'!A:AT,45,0) | AP53: YELLOW | AS53: contact_form_url | AT53: https://handspunlit.com/contact/ | AU53: Not Found | AV53: Agency only via QueryTracker. Direct emails deleted unread. | Audit note: normalized row to validated contact state.
A54: P1 | B54: 50 | C54: Pucking Wrong | D54: C.R. Jane | E54: 68.37 | F54: 5 | G54: The Pucking Wrong Number | H54: The Pucking Wrong Rookie | I54: 3.54 | J54: 93400 | K54: Tier 1 (>=20k) | M54: WEAK <30% | N54: Ice Hockey / Sports Romance | O54: Series | P54: Before 2020 | S54: Contemporary Romance (Paid) #77 | T54: 77 | U54: Needgap | V54: 2 | W54: $17,500 - $20,000 | X54: 15% | Y54: 15% - 22% | Z54: NEED CONTACT | AA54: C.R. Jane | AB54: Indie | AD54: FALSE | AF54: Stephanie Phillips, SBR Media | AG54: https://www.crjanebooks.com/ | AH54: Agent: Stephanie Phillips, SBR Media | Website: https://www.crjanebooks.com/ | AI54: =vlookup(C54,'Az working sheet Hockey Sports'!A:AT,45,0) | AP54: YELLOW | AS54: contact_form_url | AT54: https://sbrmedia.com/submissions/ | http://queryme.online/SBRMedia | AU54: Not Found | AV54: SBR Media only accepts submissions via QueryMe online portal. No direct email. | Audit note: normalized row to validated contact state.
A55: P1 | B55: 50 | C55: Swift Hat-Trick Trilogy by Hannah Cowan | D55: Hannah Cowan | E55: 29.01 | F55: 3 | G55: Lucky Hit | H55: Vital Blindside | I55: 3.6 | J55: 25700 | K55: Tier 1 (>=20k) | M55: WEAK <30% | N55: Ice Hockey / Sports Romance | O55: Short Series | P55: Before 2020 | U55: Needgap | V55: 10 | W55: No MG | X55: 12% | Y55: 12% - 18% | Z55: BELOW LENGTH THRESHOLD | AA55: Hannah Cowan | AB55: Indie | AD55: FALSE | AF55: Hannah Cowan is represented by Savannah Greenwell at Two Daisy Media | AG55: https://hannahcowanauthor.com | AH55: Agent: Hannah Cowan is represented by Savannah Greenwell at Two Daisy Media | Website: https://hannahcowanauthor.com | AI55: =vlookup(C55,'Az working sheet Hockey Sports'!A:AT,45,0) | AP55: YELLOW | AS55: agent_email | AT55: https://twodaisy.com/savannah-greenwell/ | AU55: High | AV55: Direct agent email. General: info@twodaisy.com also valid. | Audit note: normalized row to validated contact state.
A56: P3 | B56: 40 | C56: Crane Hockey | D56: Ellie Wade | E56: 65.52 | F56: 7 | G56: One Pucking Love | H56: One Pucking Moment | I56: 3.86 | J56: 1276 | K56: Tier 3 (<5k) | L56: 0.0368 | M56: WEAK <30% | N56: Ice Hockey / Sports Romance | O56: Long Series | P56: After 2020 | U56: Needgap | V56: 9 | W56: Up to $1,000 | X56: 12% | Y56: 12% - 18% | Z56: READY (low ratings) | AA56: Self-Published | AB56: Self-Pub | AC56: elliewade@elliewade.com | AD56: TRUE | AG56: https://www.elliewadeauthor.com | AH56: Email: elliewade@elliewade.com | Website: https://www.elliewadeauthor.com | AI56: =vlookup(C56,'Mail Merge'!B:J,9,0) | AJ56: 46207 | AP56: GREEN | AQ56: Dear Ellie, I'm reaching out from Pocket FM regarding the Crane Hockey series. We believe this series has strong potential for adaptation into serialized audio, a rapidly growing format structurally distinct from traditional audiobooks. We'd like to propose a partnership that includes a License Fee of $1,000 and 12% share of Revenue, details on the full offer are below. We understand many authors have granted exclusive audiobook rights (often to Audible). We are not seeking audiobook rights. Instead, we license serialized audio series adaptation rights, which are closer in nature to a TV dramatization, but in audio form, than to a traditional narrated audiobook. Rather than recording the manuscript verbatim, we create a scripted, episodic adaptation featuring dual-cast or full-cast performances, cinematic sound design, and structured cliffhanger arcs. Episodes run ~10 minutes and are released serially, with progression-based monetization. This format functions as an incremental revenue stream alongside print, ebook, KU, and audiobook sales, not in competition with them. Given the layered world-building and sustained narrative momentum in Crane Hockey, we see strong alignment with this dramatized serialized format. Pocket FM is the world's largest dedicated audio series platform, trusted by leading publishers and IP holders including Naver, Kakao, Blackstone, Recorded Books, Aethon, and China Literature. Our catalog includes globally recognized titles such as Solo Leveling, The Primal Hunter, and Omniscient Reader's Viewpoint. In the past 12 months, we've delivered: 120 billion minutes of listening 18 million monthly active users $342M in revenue 200+ million global downloads Our app is rated 4.7 on the App Store and 4.5 on Google Play. Several titles have scaled meaningfully through this model, including: My Vampire System: 1B+ listens, $100M+ revenue Saving Nora: $42M revenue The Duke's Masked Bride: 641M plays The Alpha's Bride: 415M plays You can hear an example of our production quality here: https://pocketfm.com/show/ba2d9038fc3853c464c8be7a34a0576f26145106 We are proposing: License Fee: $1,000 Revenue Share: 12% of Revenue Exclusive serialized audio series adaptation rights (distinct from audiobook rights) English language (U.S./U.K.) 5-10 year term Full IP ownership retained by the author We are focused on long-term partnerships and would welcome discussion around additional titles within your catalog as well. If of interest, I'd be glad to schedule a brief call to discuss further. Best regards, Pulaksh Khimesara US Licensing & Commissioning Pocket FM
A57: P3 | B57: 40 | C57: Denver Bashers | D57: Sarah Smith | E57: 83.28 | F57: 7 | G57: Fake As Puck | H57: So Pucking Good | I57: 3.83 | J57: 1714 | K57: Tier 3 (<5k) | M57: WEAK <30% | N57: Ice Hockey / Sports Romance | O57: Long Series | P57: After 2020 | U57: Needgap | V57: 9 | W57: 3000 | X57: 0.15 | Y57: 12% - 18% | Z57: READY (low ratings) | AA57: Sarah Smith Books | AB57: Big Pub | AC57: rights@nyliterary.com | AD57: TRUE | AE57: rights@nyliterary.com | AF57: Sarah is | AG57: https://www.sarahsmithbooks.com/ | AH57: Email: rights@nyliterary.com | Agent email: rights@nyliterary.com | Agent: Sarah is | Website: https://www.sarahsmithbooks.com/ | AI57: =vlookup(C57,'Mail Merge'!B:J,9,0) | AJ57: 46207 | AP57: GREEN | AQ57: Dear Sarah, I'm reaching out from Pocket FM regarding the Denver Bashers Series by Sarah Smith series. We believe this series has strong potential for adaptation into serialized audio, a rapidly growing format structurally distinct from traditional audiobooks. We'd like to propose a partnership that includes a License Fee of $1,000 and 12% share of Revenue, details on the full offer are below. We understand many authors have granted exclusive audiobook rights (often to Audible). We are not seeking audiobook rights. Instead, we license serialized audio series adaptation rights, which are closer in nature to a TV dramatization, but in audio form, than to a traditional narrated audiobook. Rather than recording the manuscript verbatim, we create a scripted, episodic adaptation featuring dual-cast or full-cast performances, cinematic sound design, and structured cliffhanger arcs. Episodes run ~10 minutes and are released serially, with progression-based monetization. This format functions as an incremental revenue stream alongside print, ebook, KU, and audiobook sales, not in competition with them. Given the layered world-building and sustained narrative momentum in Denver Bashers Series by Sarah Smith, we see strong alignment with this dramatized serialized format. Pocket FM is the world's largest dedicated audio series platform, trusted by leading publishers and IP holders including Naver, Kakao, Blackstone, Recorded Books, Aethon, and China Literature. Our catalog includes globally recognized titles such as Solo Leveling, The Primal Hunter, and Omniscient Reader's Viewpoint. In the past 12 months, we've delivered: 120 billion minutes of listening 18 million monthly active users $342M in revenue 200+ million global downloads Our app is rated 4.7 on the App Store and 4.5 on Google Play. Several titles have scaled meaningfully through this model, including: My Vampire System: 1B+ listens, $100M+ revenue Saving Nora: $42M revenue The Duke's Masked Bride: 641M plays The Alpha's Bride: 415M plays You can hear an example of our production quality here: https://pocketfm.com/show/ba2d9038fc3853c464c8be7a34a0576f26145106 We are proposing: License Fee: $1,000 Revenue Share: 12% of Revenue Exclusive serialized audio series adaptation rights (distinct from audiobook rights) English language (U.S./U.K.) 5-10 year term Full IP ownership retained by the author We are focused on long-term partnerships and would welcome discussion around additional titles within your catalog as well. If of interest, I'd be glad to schedule a brief call to discuss further. Best regards, Pulaksh Khimesara US Licensing & Commissioning Pocket FM
A58: P1 | B58: 65 | C58: Briar U | D58: Elle Kennedy | E58: 42.9 | F58: 4 | G58: The Chase | H58: The Dare | I58: 3.85 | J58: 271505 | K58: Tier 1 (>=20k) | M58: WEAK <30% | N58: Ice Hockey / Sports Romance | O58: Series | P58: Before 2020 | S58: Sports Romance (Paid) #3 | T58: 3 | U58: Needgap | V58: 2 | W58: $17,500 - $20,000 | X58: 15% | Y58: 15% - 22% | Z58: READY | AA58: Sourcebooks Inc | AB58: Indie | AC58: publicity@ellekennedy.com | AD58: TRUE | AE58: publicity@stmartins.com | AF58: Contact form on official website | AG58: http://ellekennedy.com/ | AH58: Email: publicity@ellekennedy.com | Agent email: publicity@stmartins.com | Agent: Contact form on official website | Website: http://ellekennedy.com/ | AI58: sent to elle for offcampus | AJ58: 46177 | AP58: GREEN | AQ58: Dear Elle, I'm reaching out from Pocket FM regarding the Briar U series. We believe this series has strong potential for adaptation into serialized audio, a rapidly growing format structurally distinct from traditional audiobooks. We'd like to propose a partnership that includes a License Fee of $20,000 and 15% share of Revenue, details on the full offer are below. We understand many authors have granted exclusive audiobook rights (often to Audible). We are not seeking audiobook rights. Instead, we license serialized audio series adaptation rights, which are closer in nature to a TV dramatization, but in audio form, than to a traditional narrated audiobook. Rather than recording the manuscript verbatim, we create a scripted, episodic adaptation featuring dual-cast or full-cast performances, cinematic sound design, and structured cliffhanger arcs. Episodes run ~10 minutes and are released serially, with progression-based monetization. This format functions as an incremental revenue stream alongside print, ebook, KU, and audiobook sales, not in competition with them. Given the layered world-building and sustained narrative momentum in Briar U, we see strong alignment with this dramatized serialized format. Pocket FM is the world's largest dedicated audio series platform, trusted by leading publishers and IP holders including Naver, Kakao, Blackstone, Recorded Books, Aethon, and China Literature. Our catalog includes globally recognized titles such as Solo Leveling, The Primal Hunter, and Omniscient Reader's Viewpoint. In the past 12 months, we've delivered: 120 billion minutes of listening 18 million monthly active users $342M in revenue 200+ million global downloads Our app is rated 4.7 on the App Store and 4.5 on Google Play. Several titles have scaled meaningfully through this model, including: My Vampire System: 1B+ listens, $100M+ revenue Saving Nora: $42M revenue The Duke's Masked Bride: 641M plays The Alpha's Bride: 415M plays You can hear an example of our production quality here: https://pocketfm.com/show/ba2d9038fc3853c464c8be7a34a0576f26145106 We are proposing: License Fee: $20,000 Revenue Share: 15% of Revenue Exclusive serialized audio series adaptation rights (distinct from audiobook rights) English language (U.S./U.K.) 5-10 year term Full IP ownership retained by the author We are focused on long-term partnerships and would welcome discussion around additional titles within your catalog as well. If of interest, I'd be glad to schedule a brief call to discuss further. Best regards, Pulaksh Khimesara US Licensing & Commissioning Pocket FM | AV58: NOTE: Already contacted Elle Kennedy for: Off-Campus
A59: P1 | B59: 65 | C59: Lakes Hockey | D59: Sloane St. James | E59: 47.28 | F59: 4 | G59: Before We Came | H59: Stand and Defend | I59: 3.9 | J59: 42377 | K59: Tier 1 (>=20k) | L59: 0.7879 | M59: STRONG >=50% | N59: Ice Hockey / Sports Romance | O59: Long Series | P59: After 2020 | U59: Needgap | V59: 2 | W59: 80000 | X59: 15% | Y59: 15% - 22% | Z59: READY | AA59: SJ Publishing | AB59: Indie | AC59: sloanestjameswrites@gmail.com | AD59: TRUE | AE59: nikki@sbrmedia.com | AF59: Nikki at sbrmedia.com | AG59: https://sloanestjames.com/ | AH59: Email: nikki@sbrmedia.com | Agent: Nikki at sbrmedia.com | Website: https://sloanestjames.com/ | AI59: sent to sloane and nikki | AJ59: 46177 | AP59: GREEN | AQ59: Dear Sloane, I'm reaching out from Pocket FM regarding the Lakes Hockey series. We believe this series has strong potential for adaptation into serialized audio, a rapidly growing format structurally distinct from traditional audiobooks. We'd like to propose a partnership that includes a License Fee of $20,000 and 15% share of Revenue, details on the full offer are below. We understand many authors have granted exclusive audiobook rights (often to Audible). We are not seeking audiobook rights. Instead, we license serialized audio series adaptation rights, which are closer in nature to a TV dramatization, but in audio form, than to a traditional narrated audiobook. Rather than recording the manuscript verbatim, we create a scripted, episodic adaptation featuring dual-cast or full-cast performances, cinematic sound design, and structured cliffhanger arcs. Episodes run ~10 minutes and are released serially, with progression-based monetization. This format functions as an incremental revenue stream alongside print, ebook, KU, and audiobook sales, not in competition with them. Given the layered world-building and sustained narrative momentum in Lakes Hockey, we see strong alignment with this dramatized serialized format. Pocket FM is the world's largest dedicated audio series platform, trusted by leading publishers and IP holders including Naver, Kakao, Blackstone, Recorded Books, Aethon, and China Literature. Our catalog includes globally recognized titles such as Solo Leveling, The Primal Hunter, and Omniscient Reader's Viewpoint. In the past 12 months, we've delivered: 120 billion minutes of listening 18 million monthly active users $342M in revenue 200+ million global downloads Our app is rated 4.7 on the App Store and 4.5 on Google Play. Several titles have scaled meaningfully through this model, including: My Vampire System: 1B+ listens, $100M+ revenue Saving Nora: $42M revenue The Duke's Masked Bride: 641M plays The Alpha's Bride: 415M plays You can hear an example of our production quality here: https://pocketfm.com/show/ba2d9038fc3853c464c8be7a34a0576f26145106 We are proposing: License Fee: $20,000 Revenue Share: 15% of Revenue Exclusive serialized audio series adaptation rights (distinct from audiobook rights) English language (U.S./U.K.) 5-10 year term Full IP ownership retained by the author We are focused on long-term partnerships and would welcome discussion around additional titles within your catalog as well. If of interest, I'd be glad to schedule a brief call to discuss further. Best regards, Pulaksh Khimesara US Licensing & Commissioning Pocket FM
A60: P1 | B60: 63 | C60: D.C. Eagles Hockey | D60: Leah Brunner | E60: 35.16 | F60: 4 | G60: Desire or Defense | H60: Secret or Shutout | I60: 3.35 | J60: 7904 | K60: Tier 2 (>=5k) | L60: 0.5857 | M60: STRONG >=50% | N60: Ice Hockey / Sports Romance | O60: Series | P60: Before 2020 | Q60: Amazon Top 50 | R60: Amazon Top 50 | U60: Needgap | V60: 10 | W60: 4000 | X60: 12% | Y60: 12% - 18% | Z60: BELOW LENGTH THRESHOLD | AA60: Lauren Runow | AB60: Indie | AC60: info@leahbrunner.com | AD60: TRUE | AE60: eva@speilburgliterary.com | AF60: John Cusick – | AG60: https://leahbrunner.com/ | AH60: Email: John@foliolit.com | Agent email: John@foliolit.com | Agent: John Cusick – | Website: https://leahbrunner.com/ | AI60: sent mail to leah and eva | AJ60: 46177 | AP60: GREEN | AQ60: Dear Leah, I'm reaching out from Pocket FM regarding the D.C. Eagles Hockey series. We believe this series has strong potential for adaptation into serialized audio, a rapidly growing format structurally distinct from traditional audiobooks. We'd like to propose a partnership that includes a License Fee of Revenue Share Only and 12% share of Revenue, details on the full offer are below. We understand many authors have granted exclusive audiobook rights (often to Audible). We are not seeking audiobook rights. Instead, we license serialized audio series adaptation rights, which are closer in nature to a TV dramatization, but in audio form, than to a traditional narrated audiobook. Rather than recording the manuscript verbatim, we create a scripted, episodic adaptation featuring dual-cast or full-cast performances, cinematic sound design, and structured cliffhanger arcs. Episodes run ~10 minutes and are released serially, with progression-based monetization. This format functions as an incremental revenue stream alongside print, ebook, KU, and audiobook sales, not in competition with them. Given the layered world-building and sustained narrative momentum in D.C. Eagles Hockey, we see strong alignment with this dramatized serialized format. Pocket FM is the world's largest dedicated audio series platform, trusted by leading publishers and IP holders including Naver, Kakao, Blackstone, Recorded Books, Aethon, and China Literature. Our catalog includes globally recognized titles such as Solo Leveling, The Primal Hunter, and Omniscient Reader's Viewpoint. In the past 12 months, we've delivered: 120 billion minutes of listening 18 million monthly active users $342M in revenue 200+ million global downloads Our app is rated 4.7 on the App Store and 4.5 on Google Play. Several titles have scaled meaningfully through this model, including: My Vampire System: 1B+ listens, $100M+ revenue Saving Nora: $42M revenue The Duke's Masked Bride: 641M plays The Alpha's Bride: 415M plays You can hear an example of our production quality here: https://pocketfm.com/show/ba2d9038fc3853c464c8be7a34a0576f26145106 We are proposing: License Fee: Revenue Share Only Revenue Share: 12% of Revenue Exclusive serialized audio series adaptation rights (distinct from audiobook rights) English language (U.S./U.K.) 5-10 year term Full IP ownership retained by the author We are focused on long-term partnerships and would welcome discussion around additional titles within your catalog as well. If of interest, I'd be glad to schedule a brief call to discuss further. Best regards, Pulaksh Khimesara US Licensing & Commissioning Pocket FM
A61: P1 | B61: 43 | C61: Hockey Guys | D61: Sarina Bowen | E61: 75.15 | F61: 4 | G61: The New Guy | H61: My Kind of Guy | I61: 3.82 | J61: 48650 | K61: Tier 1 (>=20k) | L61: 0.2479 | M61: WEAK <30% | N61: Ice Hockey / Sports Romance | O61: Series | P61: After 2020 | S61: Contemporary Romance (Paid) #72 | T61: 72 | U61: Needgap | V61: 2 | W61: $17,500 - $20,000 | X61: 15% | Y61: 15% - 22% | Z61: READY | AA61: Rennie Road Books | AB61: Self-Pub | AC61: sarina.bowen@yahoo.com | AD61: TRUE | AF61: in English is | AG61: https://sarinabowen.com | AH61: Email: sarina.bowen@yahoo.com | Agent: in English is | Website: https://sarinabowen.com | AI61: sent mail for different series, topped up to that | AJ61: 46177 | AP61: GREEN | AQ61: Dear Sarina, I'm reaching out from Pocket FM regarding the Hockey Guys series. We believe this series has strong potential for adaptation into serialized audio, a rapidly growing format structurally distinct from traditional audiobooks. We'd like to propose a partnership that includes a License Fee of $20,000 and 15% share of Revenue, details on the full offer are below. We understand many authors have granted exclusive audiobook rights (often to Audible). We are not seeking audiobook rights. Instead, we license serialized audio series adaptation rights, which are closer in nature to a TV dramatization, but in audio form, than to a traditional narrated audiobook. Rather than recording the manuscript verbatim, we create a scripted, episodic adaptation featuring dual-cast or full-cast performances, cinematic sound design, and structured cliffhanger arcs. Episodes run ~10 minutes and are released serially, with progression-based monetization. This format functions as an incremental revenue stream alongside print, ebook, KU, and audiobook sales, not in competition with them. Given the layered world-building and sustained narrative momentum in Hockey Guys, we see strong alignment with this dramatized serialized format. Pocket FM is the world's largest dedicated audio series platform, trusted by leading publishers and IP holders including Naver, Kakao, Blackstone, Recorded Books, Aethon, and China Literature. Our catalog includes globally recognized titles such as Solo Leveling, The Primal Hunter, and Omniscient Reader's Viewpoint. In the past 12 months, we've delivered: 120 billion minutes of listening 18 million monthly active users $342M in revenue 200+ million global downloads Our app is rated 4.7 on the App Store and 4.5 on Google Play. Several titles have scaled meaningfully through this model, including: My Vampire System: 1B+ listens, $100M+ revenue Saving Nora: $42M revenue The Duke's Masked Bride: 641M plays The Alpha's Bride: 415M plays You can hear an example of our production quality here: https://pocketfm.com/show/ba2d9038fc3853c464c8be7a34a0576f26145106 We are proposing: License Fee: $20,000 Revenue Share: 15% of Revenue Exclusive serialized audio series adaptation rights (distinct from audiobook rights) English language (U.S./U.K.) 5-10 year term Full IP ownership retained by the author We are focused on long-term partnerships and would welcome discussion around additional titles within your catalog as well. If of interest, I'd be glad to schedule a brief call to discuss further. Best regards, Pulaksh Khimesara US Licensing & Commissioning Pocket FM | AV61: NOTE: Already contacted Sarina Bowen for: Brooklyn Bruisers, The Ivy Years
A62: P1 | C62: Denver Dragons Series | D62: Madi Danielle | E62: 40.62 | F62: 4 | G62: The Hat Trick | H62: The Break Out | I62: 3.69 | J62: 9073 | K62: Tier 2 (>=5k) | L62: 0.2931 | M62: WEAK <30% | N62: Ice Hockey / Sports Romance | O62: Series | U62: Needgap | V62: 6 | W62: 4000 | X62: 15% | Y62: 15% - 20% | Z62: READY | AA62: Indie | AB62: Indie | AC62: anja@madidaniellewrites.com | AD62: TRUE | AG62: https://www.madidaniellewrites.com/ | AH62: Email: anja@madidaniellewrites.com | Website: https://www.madidaniellewrites.com/ | AI62: sent mail to amdi | AJ62: 46207 | AP62: GREEN | AQ62: Dear Madi, I'm reaching out from Pocket FM regarding the Denver Dragons Series series. We believe this series has strong potential for adaptation into serialized audio, a rapidly growing format structurally distinct from traditional audiobooks. We'd like to propose a partnership that includes a License Fee of $7,500 and 15% share of Revenue, details on the full offer are below. We understand many authors have granted exclusive audiobook rights (often to Audible). We are not seeking audiobook rights. Instead, we license serialized audio series adaptation rights, which are closer in nature to a TV dramatization, but in audio form, than to a traditional narrated audiobook. Rather than recording the manuscript verbatim, we create a scripted, episodic adaptation featuring dual-cast or full-cast performances, cinematic sound design, and structured cliffhanger arcs. Episodes run ~10 minutes and are released serially, with progression-based monetization. This format functions as an incremental revenue stream alongside print, ebook, KU, and audiobook sales, not in competition with them. Given the layered world-building and sustained narrative momentum in Denver Dragons Series, we see strong alignment with this dramatized serialized format. Pocket FM is the world's largest dedicated audio series platform, trusted by leading publishers and IP holders including Naver, Kakao, Blackstone, Recorded Books, Aethon, and China Literature. Our catalog includes globally recognized titles such as Solo Leveling, The Primal Hunter, and Omniscient Reader's Viewpoint. In the past 12 months, we've delivered: 120 billion minutes of listening 18 million monthly active users $342M in revenue 200+ million global downloads Our app is rated 4.7 on the App Store and 4.5 on Google Play. Several titles have scaled meaningfully through this model, including: My Vampire System: 1B+ listens, $100M+ revenue Saving Nora: $42M revenue The Duke's Masked Bride: 641M plays The Alpha's Bride: 415M plays You can hear an example of our production quality here: https://pocketfm.com/show/ba2d9038fc3853c464c8be7a34a0576f26145106 We are proposing: License Fee: $7,500 Revenue Share: 15% of Revenue Exclusive serialized audio series adaptation rights (distinct from audiobook rights) English language (U.S./U.K.) 5-10 year term Full IP ownership retained by the author We are focused on long-term partnerships and would welcome discussion around additional titles within your catalog as well. If of interest, I'd be glad to schedule a brief call to discuss further. Best regards, Pulaksh Khimesara US Licensing & Commissioning Pocket FM
A63: P1 | C63: The Cocky Kingmans | D63: Amy Award | E63: 96.72 | F63: 8 | G63: The C*ck Down the Block | H63: The Tiger in the Sack | I63: 3.72 | J63: 55199 | K63: Tier 1 (>=20k) | M63: WEAK <30% | N63: Ice Hockey / Sports Romance | O63: Long Series | U63: Needgap | V63: 1 | W63: $17,500 - $25,000 | X63: 15% | Y63: 15% - 22% | Z63: READY | AA63: Self-Pub | AB63: Self-Pub | AD63: FALSE | AF63: Mark Owen Gottlieb, Trident Media Group, LLC | AG63: https://www.authoramyaward.com | AH63: Agent: Mark Owen Gottlieb, Trident Media Group, LLC | Website: https://www.authoramyaward.com | AI63: =vlookup(C63,'Az working sheet Hockey Sports'!A:AT,45,0) | AP63: YELLOW | AQ63: Dear Amy, I'm reaching out from Pocket FM regarding the The Cocky Kingmans series. We believe this series has strong potential for adaptation into serialized audio, a rapidly growing format structurally distinct from traditional audiobooks. We'd like to propose a partnership that includes a License Fee of $25,000 and 15% share of Revenue, details on the full offer are below. We understand many authors have granted exclusive audiobook rights (often to Audible). We are not seeking audiobook rights. Instead, we license serialized audio series adaptation rights, which are closer in nature to a TV dramatization, but in audio form, than to a traditional narrated audiobook. Rather than recording the manuscript verbatim, we create a scripted, episodic adaptation featuring dual-cast or full-cast performances, cinematic sound design, and structured cliffhanger arcs. Episodes run ~10 minutes and are released serially, with progression-based monetization. This format functions as an incremental revenue stream alongside print, ebook, KU, and audiobook sales, not in competition with them. Given the layered world-building and sustained narrative momentum in The Cocky Kingmans, we see strong alignment with this dramatized serialized format. Pocket FM is the world's largest dedicated audio series platform, trusted by leading publishers and IP holders including Naver, Kakao, Blackstone, Recorded Books, Aethon, and China Literature. Our catalog includes globally recognized titles such as Solo Leveling, The Primal Hunter, and Omniscient Reader's Viewpoint. In the past 12 months, we've delivered: 120 billion minutes of listening 18 million monthly active users $342M in revenue 200+ million global downloads Our app is rated 4.7 on the App Store and 4.5 on Google Play. Several titles have scaled meaningfully through this model, including: My Vampire System: 1B+ listens, $100M+ revenue Saving Nora: $42M revenue The Duke's Masked Bride: 641M plays The Alpha's Bride: 415M plays You can hear an example of our production quality here: https://pocketfm.com/show/ba2d9038fc3853c464c8be7a34a0576f26145106 We are proposing: License Fee: $25,000 Revenue Share: 15% of Revenue Exclusive serialized audio series adaptation rights (distinct from audiobook rights) English language (U.S./U.K.) 5-10 year term Full IP ownership retained by the author We are focused on long-term partnerships and would welcome discussion around additional titles within your catalog as well. If of interest, I'd be glad to schedule a brief call to discuss further. Best regards, Pulaksh Khimesara US Licensing & Commissioning Pocket FM
A64: P1 | C64: The Atlanta Vipers Series | D64: Eliza Peake | E64: 29.7 | F64: 3 | G64: Holiday Interference | H64: Power Play | I64: 3.92 | J64: 250 | K64: Tier 3 (<5k) | L64: 84.992 | M64: STRONG >=50% | N64: Ice Hockey / Sports Romance | O64: Short Series | U64: Needgap | V64: 10 | W64: No MG | X64: 12% | Y64: 12% - 18% | Z64: BELOW LENGTH THRESHOLD | AA64: Indie | AB64: Indie | AD64: FALSE | AG64: https://elizapeake.com | AH64: Website: https://elizapeake.com | AI64: =vlookup(C64,'Az working sheet Hockey Sports'!A:AT,45,0) | AP64: YELLOW | AU64: Not Found
A65: P1 | B65: 63 | C65: The Copper Valley Thrusters | D65: Pippa Grant | E65: 47.97 | F65: 3 | G65: The Pilot & the Puck-Up | H65: Beauty and the Beefcake | I65: 4.2 | J65: 11246 | K65: Tier 2 (>=5k) | M65: WEAK <30% | N65: Ice Hockey / Sports Romance | O65: Short Series | P65: Before 2020 | U65: Needgap | V65: 6 | W65: $5,000 - $7,500 | X65: 15% | Y65: 15% - 20% | Z65: READY | AA65: Pippa Grant | AB65: Self-Pub | AC65: pipsterreport@pippagrant.com | AD65: TRUE | AE65: foreignrights@bookendsliterary.com | AF65: Jessica Alvarez at BookEnds or email foreignrights | AG65: https://www.pippagrant.com | AH65: Email: pipsterreport@pippagrant.com | Agent email: foreignrights@bookendsliterary.com | Agent: Jessica Alvarez at BookEnds or email foreignrights | Website: https://www.pippagrant.com | AI65: =vlookup(C65,'Az working sheet Hockey Sports'!A:AT,45,0) | AP65: GREEN | AQ65: Dear Pippa, I'm reaching out from Pocket FM regarding the The Copper Valley Thrusters series. We believe this series has strong potential for adaptation into serialized audio, a rapidly growing format structurally distinct from traditional audiobooks. We'd like to propose a partnership that includes a License Fee of $7,500 and 15% share of Revenue, details on the full offer are below. We understand many authors have granted exclusive audiobook rights (often to Audible). We are not seeking audiobook rights. Instead, we license serialized audio series adaptation rights, which are closer in nature to a TV dramatization, but in audio form, than to a traditional narrated audiobook. Rather than recording the manuscript verbatim, we create a scripted, episodic adaptation featuring dual-cast or full-cast performances, cinematic sound design, and structured cliffhanger arcs. Episodes run ~10 minutes and are released serially, with progression-based monetization. This format functions as an incremental revenue stream alongside print, ebook, KU, and audiobook sales, not in competition with them. Given the layered world-building and sustained narrative momentum in The Copper Valley Thrusters, we see strong alignment with this dramatized serialized format. Pocket FM is the world's largest dedicated audio series platform, trusted by leading publishers and IP holders including Naver, Kakao, Blackstone, Recorded Books, Aethon, and China Literature. Our catalog includes globally recognized titles such as Solo Leveling, The Primal Hunter, and Omniscient Reader's Viewpoint. In the past 12 months, we've delivered: 120 billion minutes of listening 18 million monthly active users $342M in revenue 200+ million global downloads Our app is rated 4.7 on the App Store and 4.5 on Google Play. Several titles have scaled meaningfully through this model, including: My Vampire System: 1B+ listens, $100M+ revenue Saving Nora: $42M revenue The Duke's Masked Bride: 641M plays The Alpha's Bride: 415M plays You can hear an example of our production quality here: https://pocketfm.com/show/ba2d9038fc3853c464c8be7a34a0576f26145106 We are proposing: License Fee: $7,500 Revenue Share: 15% of Revenue Exclusive serialized audio series adaptation rights (distinct from audiobook rights) English language (U.S./U.K.) 5-10 year term Full IP ownership retained by the author We are focused on long-term partnerships and would welcome discussion around additional titles within your catalog as well. If of interest, I'd be glad to schedule a brief call to discuss further. Best regards, Pulaksh Khimesara US Licensing & Commissioning Pocket FM
A66: P1 | C66: Fairfield U | D66: G.N. Wright | E66: 46.95 | F66: 4 | G66: The Puck Secret | H66: The Puck Player | I66: 4 | J66: 18177 | K66: Tier 2 (>=5k) | L66: 0.1231 | M66: WEAK <30% | N66: Ice Hockey / Sports Romance | O66: Series | Q66: Hockey T100 | R66: Hockey T100 | U66: Needgap | V66: 6 | W66: $5,000 - $7,500 | X66: 15% | Y66: 15% - 20% | Z66: NEED CONTACT | AA66: Indie | AB66: Indie | AD66: FALSE | AG66: https://gnwrightauthor.com | AH66: Website: https://gnwrightauthor.com | AI66: =vlookup(C66,'Az working sheet Hockey Sports'!A:AT,45,0) | AP66: YELLOW | AS66: not_found | AT66: https://www.goodreads.com/series/376618-fairfield-u | AU66: Not Found | AV66: Limited online presence. No website or email found.
A67: P1 | C67: Waylon University | D67: Ilsa Madden-Mills | E67: 38.28 | F67: 4 | G67: I Dare You | H67: I Promise You | I67: 3.84 | J67: 31111 | K67: Tier 1 (>=20k) | L67: 0.3851 | M67: MODERATE 30-50% | N67: Ice Hockey / Sports Romance | O67: Series | P67: Before 2020 | U67: Needgap | V67: 10 | W67: No MG | X67: 12% | Y67: 12% - 18% | Z67: BELOW LENGTH THRESHOLD | AA67: Indie | AB67: Indie | AD67: TRUE | AF67: Brower Literary | AG67: http://www.ilsamaddenmills.com/ | AH67: Email: Author@Ilsamaddenmills.com | Agent: Brower Literary | Website: http://www.ilsamaddenmills.com/ | AI67: =vlookup(C67,'Az working sheet Hockey Sports'!A:AT,45,0) | AP67: YELLOW | AQ67: Dear Ilsa, I'm reaching out from Pocket FM regarding the Waylon University series. We believe this series has strong potential for adaptation into serialized audio, a rapidly growing format structurally distinct from traditional audiobooks. We'd like to propose a partnership that includes a License Fee of Revenue Share Only and 12% share of Revenue, details on the full offer are below. We understand many authors have granted exclusive audiobook rights (often to Audible). We are not seeking audiobook rights. Instead, we license serialized audio series adaptation rights, which are closer in nature to a TV dramatization, but in audio form, than to a traditional narrated audiobook. Rather than recording the manuscript verbatim, we create a scripted, episodic adaptation featuring dual-cast or full-cast performances, cinematic sound design, and structured cliffhanger arcs. Episodes run ~10 minutes and are released serially, with progression-based monetization. This format functions as an incremental revenue stream alongside print, ebook, KU, and audiobook sales, not in competition with them. Given the layered world-building and sustained narrative momentum in Waylon University, we see strong alignment with this dramatized serialized format. Pocket FM is the world's largest dedicated audio series platform, trusted by leading publishers and IP holders including Naver, Kakao, Blackstone, Recorded Books, Aethon, and China Literature. Our catalog includes globally recognized titles such as Solo Leveling, The Primal Hunter, and Omniscient Reader's Viewpoint. In the past 12 months, we've delivered: 120 billion minutes of listening 18 million monthly active users $342M in revenue 200+ million global downloads Our app is rated 4.7 on the App Store and 4.5 on Google Play. Several titles have scaled meaningfully through this model, including: My Vampire System: 1B+ listens, $100M+ revenue Saving Nora: $42M revenue The Duke's Masked Bride: 641M plays The Alpha's Bride: 415M plays You can hear an example of our production quality here: https://pocketfm.com/show/ba2d9038fc3853c464c8be7a34a0576f26145106 We are proposing: License Fee: Revenue Share Only Revenue Share: 12% of Revenue Exclusive serialized audio series adaptation rights (distinct from audiobook rights) English language (U.S./U.K.) 5-10 year term Full IP ownership retained by the author We are focused on long-term partnerships and would welcome discussion around additional titles within your catalog as well. If of interest, I'd be glad to schedule a brief call to discuss further. Best regards, Pulaksh Khimesara US Licensing & Commissioning Pocket FM | AS67: contact_form_url | AT67: https://ilsamaddenmills.com/contact | AU67: Not Found | AV67: Audit note: normalized row to validated contact state.
A68: P1 | B68: 55 | C68: Bears Hockey | D68: Kelly Jamieson | E68: 20.25 | F68: 3 | G68: Must Love Dogs...and Hockey | H68: Talk Hockey to Me | I68: 4.06 | J68: 666432 | K68: Tier 1 (>=20k) | M68: DATA_SCALE_MISMATCH | N68: Ice Hockey / Sports Romance | O68: Short Series | P68: After 2020 | U68: Needgap | V68: 10 | W68: No MG | X68: 12% | Y68: 12% - 18% | Z68: BELOW LENGTH THRESHOLD | AA68: Kelly Jamieson | AB68: Indie | AC68: info@kellyjamieson.com | AD68: TRUE | AF68: Contact form on official website | AG68: https://kellyjamieson.com | AH68: Email: info@kellyjamieson.com | Agent: Contact form on official website | Website: https://kellyjamieson.com | AI68: =vlookup(C68,'Az working sheet Hockey Sports'!A:AT,45,0) | AP68: GREEN | AQ68: Dear Kelly, I'm reaching out from Pocket FM regarding the Bears Hockey series. We believe this series has strong potential for adaptation into serialized audio, a rapidly growing format structurally distinct from traditional audiobooks. We'd like to propose a partnership that includes a License Fee of Revenue Share Only and 12% share of Revenue, details on the full offer are below. We understand many authors have granted exclusive audiobook rights (often to Audible). We are not seeking audiobook rights. Instead, we license serialized audio series adaptation rights, which are closer in nature to a TV dramatization, but in audio form, than to a traditional narrated audiobook. Rather than recording the manuscript verbatim, we create a scripted, episodic adaptation featuring dual-cast or full-cast performances, cinematic sound design, and structured cliffhanger arcs. Episodes run ~10 minutes and are released serially, with progression-based monetization. This format functions as an incremental revenue stream alongside print, ebook, KU, and audiobook sales, not in competition with them. Given the layered world-building and sustained narrative momentum in Bears Hockey, we see strong alignment with this dramatized serialized format. Pocket FM is the world's largest dedicated audio series platform, trusted by leading publishers and IP holders including Naver, Kakao, Blackstone, Recorded Books, Aethon, and China Literature. Our catalog includes globally recognized titles such as Solo Leveling, The Primal Hunter, and Omniscient Reader's Viewpoint. In the past 12 months, we've delivered: 120 billion minutes of listening 18 million monthly active users $342M in revenue 200+ million global downloads Our app is rated 4.7 on the App Store and 4.5 on Google Play. Several titles have scaled meaningfully through this model, including: My Vampire System: 1B+ listens, $100M+ revenue Saving Nora: $42M revenue The Duke's Masked Bride: 641M plays The Alpha's Bride: 415M plays You can hear an example of our production quality here: https://pocketfm.com/show/ba2d9038fc3853c464c8be7a34a0576f26145106 We are proposing: License Fee: Revenue Share Only Revenue Share: 12% of Revenue Exclusive serialized audio series adaptation rights (distinct from audiobook rights) English language (U.S./U.K.) 5-10 year term Full IP ownership retained by the author We are focused on long-term partnerships and would welcome discussion around additional titles within your catalog as well. If of interest, I'd be glad to schedule a brief call to discuss further. Best regards, Pulaksh Khimesara US Licensing & Commissioning Pocket FM | AS68: contact_form_url | AT68: https://www.kellyjamieson.com/contact | AU68: Not Found | AV68: NOTE: Already contacted Kelly Jamieson for: Heller Brothers Hockey | Already outreached for this author on: Heller Brothers Hockey | Audit note: normalized row to validated contact state.
A69: P1 | B69: 43 | C69: Central State Football | D69: Jaqueline Snowe | E69: 35.04 | F69: 3 | G69: First Meet Foul | H69: Scoring Forever | I69: 3.68 | J69: 6943 | K69: Tier 2 (>=5k) | L69: 0.247 | M69: WEAK <30% | N69: Ice Hockey / Sports Romance | O69: Short Series | P69: After 2020 | U69: Needgap | V69: 10 | W69: No MG | X69: 12% | Y69: 12% - 18% | Z69: BELOW LENGTH THRESHOLD | AA69: Jaqueline Snowe | AB69: Indie | AC69: jsnowecontact@gmail.com | AD69: TRUE | AF69: Contact form on official website | AG69: http://www.jaquelinesnowe.com | AH69: Email: jsnowecontact@gmail.com | Agent: Contact form on official website | Website: http://www.jaquelinesnowe.com | AI69: =vlookup(C69,'Az working sheet Hockey Sports'!A:AT,45,0) | AP69: GREEN | AQ69: Dear Jaqueline, I'm reaching out from Pocket FM regarding the Central State Football series. We believe this series has strong potential for adaptation into serialized audio, a rapidly growing format structurally distinct from traditional audiobooks. We'd like to propose a partnership that includes a License Fee of Revenue Share Only and 12% share of Revenue, details on the full offer are below. We understand many authors have granted exclusive audiobook rights (often to Audible). We are not seeking audiobook rights. Instead, we license serialized audio series adaptation rights, which are closer in nature to a TV dramatization, but in audio form, than to a traditional narrated audiobook. Rather than recording the manuscript verbatim, we create a scripted, episodic adaptation featuring dual-cast or full-cast performances, cinematic sound design, and structured cliffhanger arcs. Episodes run ~10 minutes and are released serially, with progression-based monetization. This format functions as an incremental revenue stream alongside print, ebook, KU, and audiobook sales, not in competition with them. Given the layered world-building and sustained narrative momentum in Central State Football, we see strong alignment with this dramatized serialized format. Pocket FM is the world's largest dedicated audio series platform, trusted by leading publishers and IP holders including Naver, Kakao, Blackstone, Recorded Books, Aethon, and China Literature. Our catalog includes globally recognized titles such as Solo Leveling, The Primal Hunter, and Omniscient Reader's Viewpoint. In the past 12 months, we've delivered: 120 billion minutes of listening 18 million monthly active users $342M in revenue 200+ million global downloads Our app is rated 4.7 on the App Store and 4.5 on Google Play. Several titles have scaled meaningfully through this model, including: My Vampire System: 1B+ listens, $100M+ revenue Saving Nora: $42M revenue The Duke's Masked Bride: 641M plays The Alpha's Bride: 415M plays You can hear an example of our production quality here: https://pocketfm.com/show/ba2d9038fc3853c464c8be7a34a0576f26145106 We are proposing: License Fee: Revenue Share Only Revenue Share: 12% of Revenue Exclusive serialized audio series adaptation rights (distinct from audiobook rights) English language (U.S./U.K.) 5-10 year term Full IP ownership retained by the author We are focused on long-term partnerships and would welcome discussion around additional titles within your catalog as well. If of interest, I'd be glad to schedule a brief call to discuss further. Best regards, Pulaksh Khimesara US Licensing & Commissioning Pocket FM | AR69: jsnowecontact@gmail.com | AS69: author_email | AT69: https://vertexaisearch.cloud.google.com/grounding-api-redirect/AUZIYQF_F8Ooi22g93zlvnH8RY8gSJrMmNz2XLqN793AQkMeh11S5akp8AvkQQA-oeE9QKQXgAtQsLsBTYD2dTEukzYFl7F06ua_0jmF9uLSTrmd-s9gkmmgZ1sD8JLYxvbw1dFg1-3BxA== | AU69: High
A70: P1 | C70: The Ottawa Otters | D70: K.M. Gillis | E70: 32.31 | F70: 3 | G70: O Goalie Night | H70: Faking Seasons Bright | I70: 4.03 | J70: 9476 | K70: Tier 2 (>=5k) | M70: WEAK <30% | N70: Ice Hockey / Sports Romance | O70: Short Series | U70: Needgap | V70: 10 | W70: No MG | X70: 12% | Y70: 12% - 18% | Z70: BELOW LENGTH THRESHOLD | AA70: Self Pub | AB70: Self-Pub | AD70: TRUE | AG70: https://kmgillis.com | AH70: Email: kmgilliswrites@gmail.com | Website: https://kmgillis.com | AI70: =vlookup(C70,'Az working sheet Hockey Sports'!A:AT,45,0) | AP70: GREEN | AQ70: Dear K.M., I'm reaching out from Pocket FM regarding the The Ottawa Otters series. We believe this series has strong potential for adaptation into serialized audio, a rapidly growing format structurally distinct from traditional audiobooks. We'd like to propose a partnership that includes a License Fee of Revenue Share Only and 12% share of Revenue, details on the full offer are below. We understand many authors have granted exclusive audiobook rights (often to Audible). We are not seeking audiobook rights. Instead, we license serialized audio series adaptation rights, which are closer in nature to a TV dramatization, but in audio form, than to a traditional narrated audiobook. Rather than recording the manuscript verbatim, we create a scripted, episodic adaptation featuring dual-cast or full-cast performances, cinematic sound design, and structured cliffhanger arcs. Episodes run ~10 minutes and are released serially, with progression-based monetization. This format functions as an incremental revenue stream alongside print, ebook, KU, and audiobook sales, not in competition with them. Given the layered world-building and sustained narrative momentum in The Ottawa Otters, we see strong alignment with this dramatized serialized format. Pocket FM is the world's largest dedicated audio series platform, trusted by leading publishers and IP holders including Naver, Kakao, Blackstone, Recorded Books, Aethon, and China Literature. Our catalog includes globally recognized titles such as Solo Leveling, The Primal Hunter, and Omniscient Reader's Viewpoint. In the past 12 months, we've delivered: 120 billion minutes of listening 18 million monthly active users $342M in revenue 200+ million global downloads Our app is rated 4.7 on the App Store and 4.5 on Google Play. Several titles have scaled meaningfully through this model, including: My Vampire System: 1B+ listens, $100M+ revenue Saving Nora: $42M revenue The Duke's Masked Bride: 641M plays The Alpha's Bride: 415M plays You can hear an example of our production quality here: https://pocketfm.com/show/ba2d9038fc3853c464c8be7a34a0576f26145106 We are proposing: License Fee: Revenue Share Only Revenue Share: 12% of Revenue Exclusive serialized audio series adaptation rights (distinct from audiobook rights) English language (U.S./U.K.) 5-10 year term Full IP ownership retained by the author We are focused on long-term partnerships and would welcome discussion around additional titles within your catalog as well. If of interest, I'd be glad to schedule a brief call to discuss further. Best regards, Pulaksh Khimesara US Licensing & Commissioning Pocket FM | AS70: author_email | AT70: https://vertexaisearch.cloud.google.com/grounding-api-redirect/AUZIYQEu1MsbwoebdvFC78-rsLMWAMB_kTKryq8QfXzDZnQ3csBrJMqJaKfzIYHYc3EGNPhpuodWzucQEwBGg3h9sQZ9qMPywRbcucTJ58Rk3HjtnzgVakS_-owevL_284pun9g= | AU70: High | AV70: Audit note: normalized row to validated contact state.
A71: P1 | C71: Washington Wolves | D71: Karla Sorensen | E71: 26.16 | F71: 3 | G71: The Bombshell Effect | H71: The Marriage Effect | I71: 3.85 | J71: 24718 | K71: Tier 1 (>=20k) | L71: 0.1191 | M71: WEAK <30% | N71: Ice Hockey / Sports Romance | O71: Short Series | U71: Needgap | V71: 10 | W71: No MG | X71: 12% | Y71: 12% - 18% | Z71: BELOW LENGTH THRESHOLD | AA71: Self Pub | AB71: Self-Pub | AC71: georgana@theseymouragency.com | AD71: TRUE | AE71: georgana@theseymouragency.com | AF71: Bryn Donovan | AG71: https://karlasorensen.com | AH71: Email: georgana@theseymouragency.com | Agent email: georgana@theseymouragency.com | Website: https://karlasorensen.com | AI71: =vlookup(C71,'Az working sheet Hockey Sports'!A:AT,45,0) | AP71: GREEN | AQ71: Dear Karla, I'm reaching out from Pocket FM regarding the Washington Wolves series. We believe this series has strong potential for adaptation into serialized audio, a rapidly growing format structurally distinct from traditional audiobooks. We'd like to propose a partnership that includes a License Fee of Revenue Share Only and 12% share of Revenue, details on the full offer are below. We understand many authors have granted exclusive audiobook rights (often to Audible). We are not seeking audiobook rights. Instead, we license serialized audio series adaptation rights, which are closer in nature to a TV dramatization, but in audio form, than to a traditional narrated audiobook. Rather than recording the manuscript verbatim, we create a scripted, episodic adaptation featuring dual-cast or full-cast performances, cinematic sound design, and structured cliffhanger arcs. Episodes run ~10 minutes and are released serially, with progression-based monetization. This format functions as an incremental revenue stream alongside print, ebook, KU, and audiobook sales, not in competition with them. Given the layered world-building and sustained narrative momentum in Washington Wolves, we see strong alignment with this dramatized serialized format. Pocket FM is the world's largest dedicated audio series platform, trusted by leading publishers and IP holders including Naver, Kakao, Blackstone, Recorded Books, Aethon, and China Literature. Our catalog includes globally recognized titles such as Solo Leveling, The Primal Hunter, and Omniscient Reader's Viewpoint. In the past 12 months, we've delivered: 120 billion minutes of listening 18 million monthly active users $342M in revenue 200+ million global downloads Our app is rated 4.7 on the App Store and 4.5 on Google Play. Several titles have scaled meaningfully through this model, including: My Vampire System: 1B+ listens, $100M+ revenue Saving Nora: $42M revenue The Duke's Masked Bride: 641M plays The Alpha's Bride: 415M plays You can hear an example of our production quality here: https://pocketfm.com/show/ba2d9038fc3853c464c8be7a34a0576f26145106 We are proposing: License Fee: Revenue Share Only Revenue Share: 12% of Revenue Exclusive serialized audio series adaptation rights (distinct from audiobook rights) English language (U.S./U.K.) 5-10 year term Full IP ownership retained by the author We are focused on long-term partnerships and would welcome discussion around additional titles within your catalog as well. If of interest, I'd be glad to schedule a brief call to discuss further. Best regards, Pulaksh Khimesara US Licensing & Commissioning Pocket FM | AR71: georgana@theseymouragency.com | AS71: author_email | AT71: http://www.karlasorensen.com/contact | AU71: High
A72: P1 | C72: Dare | D72: Shantel Tessier | E72: 28.17 | F72: 3 | G72: I Dare You | H72: If You Dare | I72: 4.16 | J72: 22011 | K72: Tier 1 (>=20k) | M72: WEAK <30% | N72: Ice Hockey / Sports Romance | O72: Short Series | U72: Needgap | V72: 10 | W72: No MG | X72: 12% | Y72: 12% - 18% | Z72: BELOW LENGTH THRESHOLD | AA72: Indie | AB72: Indie | AD72: TRUE | AF72: Contact form on official website | AG72: https://shanteltessier.com | AH72: Email: shanteltessierlicensing@gmail.com | Agent: Contact form on official website | Website: https://shanteltessier.com | AI72: =vlookup(C72,'Az working sheet Hockey Sports'!A:AT,45,0) | AP72: GREEN | AQ72: Dear Shantel, I'm reaching out from Pocket FM regarding the Dare series. We believe this series has strong potential for adaptation into serialized audio, a rapidly growing format structurally distinct from traditional audiobooks. We'd like to propose a partnership that includes a License Fee of Revenue Share Only and 12% share of Revenue, details on the full offer are below. We understand many authors have granted exclusive audiobook rights (often to Audible). We are not seeking audiobook rights. Instead, we license serialized audio series adaptation rights, which are closer in nature to a TV dramatization, but in audio form, than to a traditional narrated audiobook. Rather than recording the manuscript verbatim, we create a scripted, episodic adaptation featuring dual-cast or full-cast performances, cinematic sound design, and structured cliffhanger arcs. Episodes run ~10 minutes and are released serially, with progression-based monetization. This format functions as an incremental revenue stream alongside print, ebook, KU, and audiobook sales, not in competition with them. Given the layered world-building and sustained narrative momentum in Dare, we see strong alignment with this dramatized serialized format. Pocket FM is the world's largest dedicated audio series platform, trusted by leading publishers and IP holders including Naver, Kakao, Blackstone, Recorded Books, Aethon, and China Literature. Our catalog includes globally recognized titles such as Solo Leveling, The Primal Hunter, and Omniscient Reader's Viewpoint. In the past 12 months, we've delivered: 120 billion minutes of listening 18 million monthly active users $342M in revenue 200+ million global downloads Our app is rated 4.7 on the App Store and 4.5 on Google Play. Several titles have scaled meaningfully through this model, including: My Vampire System: 1B+ listens, $100M+ revenue Saving Nora: $42M revenue The Duke's Masked Bride: 641M plays The Alpha's Bride: 415M plays You can hear an example of our production quality here: https://pocketfm.com/show/ba2d9038fc3853c464c8be7a34a0576f26145106 We are proposing: License Fee: Revenue Share Only Revenue Share: 12% of Revenue Exclusive serialized audio series adaptation rights (distinct from audiobook rights) English language (U.S./U.K.) 5-10 year term Full IP ownership retained by the author We are focused on long-term partnerships and would welcome discussion around additional titles within your catalog as well. If of interest, I'd be glad to schedule a brief call to discuss further. Best regards, Pulaksh Khimesara US Licensing & Commissioning Pocket FM | AS72: agent_email | AT72: https://vertexaisearch.cloud.google.com/grounding-api-redirect/AUZIYQHXgdg4hCZdnwP6OS80dRUvOuc97cHjtG_BIWDocu2jFs2Q9SO7lAobWcEH8eDWnGRrD7mHNJW_kubdz9gr0fgG1skWfZ8qYxvdU9I--waPO0qtBu49_NPDelD5AZp52PI= | AU72: Medium | AV72: Audit note: normalized row to validated contact state.
A73: P1 | C73: The Exception | D73: Adriana Locke | E73: 20.94 | F73: 2 | G73: The Exception | H73: The Perception | I73: 4.07 | J73: 5909 | K73: Tier 2 (>=5k) | M73: WEAK <30% | N73: Ice Hockey / Sports Romance | O73: Short Series | S73: Sports Romance (Paid) #73 | T73: 73 | U73: Needgap | V73: 10 | W73: No MG | X73: 12% | Y73: 12% - 18% | Z73: BELOW LENGTH THRESHOLD | AA73: Indie | AB73: Indie | AD73: TRUE | AF73: Contact form on official website | AG73: https://adrianalocke.com | AH73: Email: authoradrianalocke@gmail.com | Agent email: Georgana@theseymouragency.com | Agent: Contact form on official website | Website: https://adrianalocke.com | AI73: =vlookup(C73,'Az working sheet Hockey Sports'!A:AT,45,0) | AP73: GREEN | AQ73: Dear Adriana, I'm reaching out from Pocket FM regarding the The Exception series. We believe this series has strong potential for adaptation into serialized audio, a rapidly growing format structurally distinct from traditional audiobooks. We'd like to propose a partnership that includes a License Fee of Revenue Share Only and 12% share of Revenue, details on the full offer are below. We understand many authors have granted exclusive audiobook rights (often to Audible). We are not seeking audiobook rights. Instead, we license serialized audio series adaptation rights, which are closer in nature to a TV dramatization, but in audio form, than to a traditional narrated audiobook. Rather than recording the manuscript verbatim, we create a scripted, episodic adaptation featuring dual-cast or full-cast performances, cinematic sound design, and structured cliffhanger arcs. Episodes run ~10 minutes and are released serially, with progression-based monetization. This format functions as an incremental revenue stream alongside print, ebook, KU, and audiobook sales, not in competition with them. Given the layered world-building and sustained narrative momentum in The Exception, we see strong alignment with this dramatized serialized format. Pocket FM is the world's largest dedicated audio series platform, trusted by leading publishers and IP holders including Naver, Kakao, Blackstone, Recorded Books, Aethon, and China Literature. Our catalog includes globally recognized titles such as Solo Leveling, The Primal Hunter, and Omniscient Reader's Viewpoint. In the past 12 months, we've delivered: 120 billion minutes of listening 18 million monthly active users $342M in revenue 200+ million global downloads Our app is rated 4.7 on the App Store and 4.5 on Google Play. Several titles have scaled meaningfully through this model, including: My Vampire System: 1B+ listens, $100M+ revenue Saving Nora: $42M revenue The Duke's Masked Bride: 641M plays The Alpha's Bride: 415M plays You can hear an example of our production quality here: https://pocketfm.com/show/ba2d9038fc3853c464c8be7a34a0576f26145106 We are proposing: License Fee: Revenue Share Only Revenue Share: 12% of Revenue Exclusive serialized audio series adaptation rights (distinct from audiobook rights) English language (U.S./U.K.) 5-10 year term Full IP ownership retained by the author We are focused on long-term partnerships and would welcome discussion around additional titles within your catalog as well. If of interest, I'd be glad to schedule a brief call to discuss further. Best regards, Pulaksh Khimesara US Licensing & Commissioning Pocket FM | AS73: contact_form_url | AT73: https://adrianalocke.com/contact/ | AU73: Not Found | AV73: Audit note: normalized row to validated contact state.
A74: P1 | C74: Seattle Phantom Football | D74: Maggie Rawdon | E74: 33.6 | F74: 3 | G74: Pick Six | H74: Wild Card | I74: 4.1 | J74: 145 | K74: Tier 3 (<5k) | L74: 33.7103 | M74: STRONG >=50% | N74: Ice Hockey / Sports Romance | O74: Short Series | U74: Needgap | V74: 10 | W74: No MG | X74: 12% | Y74: 12% - 18% | Z74: BELOW LENGTH THRESHOLD | AA74: Indie | AB74: Indie | AD74: FALSE | AF74: NONE AGENT_EMAIL: NONE WEBSITE: [ | AG74: https://maggierawdon.com | AH74: Website: https://maggierawdon.com | AI74: =vlookup(C74,'Az working sheet Hockey Sports'!A:AT,45,0) | AP74: YELLOW | AU74: Not Found
A75: P1 | C75: Breaking the Ice: A Sweet Small Town Hockey Romcom: Love on Thin Ice | D75: Kandi Steiner | E75: 24.06 | F75: 2 | G75: The Wrong Game | H75: The Right Player | I75: 3.83 | J75: 22432 | K75: Tier 1 (>=20k) | M75: WEAK <30% | N75: Ice Hockey / Sports Romance | O75: Short Series | S75: Sports Romance (Paid) #77 | T75: 77 | U75: Needgap | V75: 10 | W75: No MG | X75: 12% | Y75: 12% - 18% | Z75: BELOW LENGTH THRESHOLD | AB75: Indie | AD75: TRUE | AF75: Ariele Fredman | AG75: http://kandisteiner.com/ | AH75: Email: ariele.fredman@unitedtalent.com | Agent email: ariele.fredman@unitedtalent.com | Agent: Ariele Fredman | Website: http://kandisteiner.com/ | AI75: =vlookup(C75,'Az working sheet Hockey Sports'!A:AT,45,0) | AP75: GREEN | AQ75: Dear Kandi, I'm reaching out from Pocket FM regarding the Breaking the Ice: A Sweet Small Town Hockey Romcom: Love on Thin Ice series. We believe this series has strong potential for adaptation into serialized audio, a rapidly growing format structurally distinct from traditional audiobooks. We'd like to propose a partnership that includes a License Fee of Revenue Share Only and 12% share of Revenue, details on the full offer are below. We understand many authors have granted exclusive audiobook rights (often to Audible). We are not seeking audiobook rights. Instead, we license serialized audio series adaptation rights, which are closer in nature to a TV dramatization, but in audio form, than to a traditional narrated audiobook. Rather than recording the manuscript verbatim, we create a scripted, episodic adaptation featuring dual-cast or full-cast performances, cinematic sound design, and structured cliffhanger arcs. Episodes run ~10 minutes and are released serially, with progression-based monetization. This format functions as an incremental revenue stream alongside print, ebook, KU, and audiobook sales, not in competition with them. Given the layered world-building and sustained narrative momentum in Breaking the Ice: A Sweet Small Town Hockey Romcom: Love on Thin Ice, we see strong alignment with this dramatized serialized format. Pocket FM is the world's largest dedicated audio series platform, trusted by leading publishers and IP holders including Naver, Kakao, Blackstone, Recorded Books, Aethon, and China Literature. Our catalog includes globally recognized titles such as Solo Leveling, The Primal Hunter, and Omniscient Reader's Viewpoint. In the past 12 months, we've delivered: 120 billion minutes of listening 18 million monthly active users $342M in revenue 200+ million global downloads Our app is rated 4.7 on the App Store and 4.5 on Google Play. Several titles have scaled meaningfully through this model, including: My Vampire System: 1B+ listens, $100M+ revenue Saving Nora: $42M revenue The Duke's Masked Bride: 641M plays The Alpha's Bride: 415M plays You can hear an example of our production quality here: https://pocketfm.com/show/ba2d9038fc3853c464c8be7a34a0576f26145106 We are proposing: License Fee: Revenue Share Only Revenue Share: 12% of Revenue Exclusive serialized audio series adaptation rights (distinct from audiobook rights) English language (U.S./U.K.) 5-10 year term Full IP ownership retained by the author We are focused on long-term partnerships and would welcome discussion around additional titles within your catalog as well. If of interest, I'd be glad to schedule a brief call to discuss further. Best regards, Pulaksh Khimesara US Licensing & Commissioning Pocket FM | AS75: agent_email | AT75: https://vertexaisearch.cloud.google.com/grounding-api-redirect/AUZIYQHWgLziYscb75fEvDbTx8DD_klh8kAt45GOjV3wdDPcKGuklJiyvnya4y_RIK6tUn8YJgiZFKMpNfpsqaB1O9ghBJuloCCFMcO9PWxekPJJCCKqK4UA-k3gtPGs8g== | AU75: Medium | AV75: NOTE: Already contacted Kandi Steiner for: Kings of the Ice | Already outreached for this author on: Kings of the Ice | Audit note: normalized row to validated contact state.
A76: P1 | B76: 55 | C76: Lakeside University Hockey | D76: Avery Keelan | E76: 45.36 | F76: 1 | G76: The Enforcer | H76: The Enforcer | I76: 3.79 | J76: 32110 | K76: Tier 1 (>=20k) | M76: WEAK <30% | N76: Ice Hockey / Sports Romance | O76: Standalone | P76: After 2020 | U76: Needgap | V76: 2 | W76: $17,500 - $20,000 | X76: 15% | Y76: 15% - 22% | Z76: READY | AA76: Avery Keelan | AB76: Indie | AC76: averykeelanwrites@gmail.com | AD76: TRUE | AE76: jessica@dijkstraagency.com | AF76: Jessica Watterson, Sandra Dijkstra Literary Agency | AG76: https://averykeelan.com/ | AH76: Email: averykeelanwrites@gmail.com | Agent email: jessica@dijkstraagency.com | Agent: Jessica Watterson, Sandra Dijkstra Literary Agency | Website: https://averykeelan.com/ | AI76: =vlookup(C76,'Az working sheet Hockey Sports'!A:AT,45,0) | AP76: GREEN | AQ76: Dear Avery, I'm reaching out from Pocket FM regarding the Lakeside University Hockey series. We believe this series has strong potential for adaptation into serialized audio, a rapidly growing format structurally distinct from traditional audiobooks. We'd like to propose a partnership that includes a License Fee of $20,000 and 15% share of Revenue, details on the full offer are below. We understand many authors have granted exclusive audiobook rights (often to Audible). We are not seeking audiobook rights. Instead, we license serialized audio series adaptation rights, which are closer in nature to a TV dramatization, but in audio form, than to a traditional narrated audiobook. Rather than recording the manuscript verbatim, we create a scripted, episodic adaptation featuring dual-cast or full-cast performances, cinematic sound design, and structured cliffhanger arcs. Episodes run ~10 minutes and are released serially, with progression-based monetization. This format functions as an incremental revenue stream alongside print, ebook, KU, and audiobook sales, not in competition with them. Given the layered world-building and sustained narrative momentum in Lakeside University Hockey, we see strong alignment with this dramatized serialized format. Pocket FM is the world's largest dedicated audio series platform, trusted by leading publishers and IP holders including Naver, Kakao, Blackstone, Recorded Books, Aethon, and China Literature. Our catalog includes globally recognized titles such as Solo Leveling, The Primal Hunter, and Omniscient Reader's Viewpoint. In the past 12 months, we've delivered: 120 billion minutes of listening 18 million monthly active users $342M in revenue 200+ million global downloads Our app is rated 4.7 on the App Store and 4.5 on Google Play. Several titles have scaled meaningfully through this model, including: My Vampire System: 1B+ listens, $100M+ revenue Saving Nora: $42M revenue The Duke's Masked Bride: 641M plays The Alpha's Bride: 415M plays You can hear an example of our production quality here: https://pocketfm.com/show/ba2d9038fc3853c464c8be7a34a0576f26145106 We are proposing: License Fee: $20,000 Revenue Share: 15% of Revenue Exclusive serialized audio series adaptation rights (distinct from audiobook rights) English language (U.S./U.K.) 5-10 year term Full IP ownership retained by the author We are focused on long-term partnerships and would welcome discussion around additional titles within your catalog as well. If of interest, I'd be glad to schedule a brief call to discuss further. Best regards, Pulaksh Khimesara US Licensing & Commissioning Pocket FM
A77: P1 | C77: The Players | D77: Monica Murphy | E77: 35.94 | F77: 3 | G77: Playing Hard to Get | H77: Playing to Win | I77: 3.74 | J77: 31926 | K77: Tier 1 (>=20k) | L77: 0.4681 | M77: MODERATE 30-50% | N77: Ice Hockey / Sports Romance | O77: Short Series | U77: Needgap | V77: 10 | W77: No MG | X77: 12% | Y77: 12% - 18% | Z77: BELOW LENGTH THRESHOLD | AA77: Self Pub | AB77: Self-Pub | AD77: FALSE | AF77: Trident Media Group | AG77: http://monicamurphyauthor.com | AH77: Agent: Trident Media Group | Website: http://monicamurphyauthor.com | AI77: =vlookup(C77,'Az working sheet Hockey Sports'!A:AT,45,0) | AP77: YELLOW | AQ77: Dear Monica, I'm reaching out from Pocket FM regarding the The Players series. We believe this series has strong potential for adaptation into serialized audio, a rapidly growing format structurally distinct from traditional audiobooks. We'd like to propose a partnership that includes a License Fee of Revenue Share Only and 12% share of Revenue, details on the full offer are below. We understand many authors have granted exclusive audiobook rights (often to Audible). We are not seeking audiobook rights. Instead, we license serialized audio series adaptation rights, which are closer in nature to a TV dramatization, but in audio form, than to a traditional narrated audiobook. Rather than recording the manuscript verbatim, we create a scripted, episodic adaptation featuring dual-cast or full-cast performances, cinematic sound design, and structured cliffhanger arcs. Episodes run ~10 minutes and are released serially, with progression-based monetization. This format functions as an incremental revenue stream alongside print, ebook, KU, and audiobook sales, not in competition with them. Given the layered world-building and sustained narrative momentum in The Players, we see strong alignment with this dramatized serialized format. Pocket FM is the world's largest dedicated audio series platform, trusted by leading publishers and IP holders including Naver, Kakao, Blackstone, Recorded Books, Aethon, and China Literature. Our catalog includes globally recognized titles such as Solo Leveling, The Primal Hunter, and Omniscient Reader's Viewpoint. In the past 12 months, we've delivered: 120 billion minutes of listening 18 million monthly active users $342M in revenue 200+ million global downloads Our app is rated 4.7 on the App Store and 4.5 on Google Play. Several titles have scaled meaningfully through this model, including: My Vampire System: 1B+ listens, $100M+ revenue Saving Nora: $42M revenue The Duke's Masked Bride: 641M plays The Alpha's Bride: 415M plays You can hear an example of our production quality here: https://pocketfm.com/show/ba2d9038fc3853c464c8be7a34a0576f26145106 We are proposing: License Fee: Revenue Share Only Revenue Share: 12% of Revenue Exclusive serialized audio series adaptation rights (distinct from audiobook rights) English language (U.S./U.K.) 5-10 year term Full IP ownership retained by the author We are focused on long-term partnerships and would welcome discussion around additional titles within your catalog as well. If of interest, I'd be glad to schedule a brief call to discuss further. Best regards, Pulaksh Khimesara US Licensing & Commissioning Pocket FM | AU77: Not Found
A78: P1 | C78: A Scoring Chance Series | D78: Marie M. | E78: 11.82 | F78: 1 | G78: High Sticking the Heart | H78: High Sticking the Heart | I78: 4.11 | J78: 4093 | K78: Tier 3 (<5k) | L78: 1 | M78: STRONG >=50% | N78: Ice Hockey / Sports Romance | O78: Standalone | U78: Needgap | V78: 10 | W78: No MG | X78: 12% | Y78: 12% - 18% | Z78: BELOW LENGTH THRESHOLD | AA78: Self Pub | AB78: Self-Pub | AC78: marieannlavender@gmail.com | AD78: TRUE | AF78: Marie Brown, Marie Brown Associates | AG78: https://mariemwrites.com | AH78: Email: marieannlavender@gmail.com | Agent: Marie Brown, Marie Brown Associates | Website: https://mariemwrites.com | AI78: =vlookup(C78,'Az working sheet Hockey Sports'!A:AT,45,0) | AP78: GREEN | AQ78: Dear Marie, I'm reaching out from Pocket FM regarding the A Scoring Chance Series series. We believe this series has strong potential for adaptation into serialized audio, a rapidly growing format structurally distinct from traditional audiobooks. We'd like to propose a partnership that includes a License Fee of Revenue Share Only and 12% share of Revenue, details on the full offer are below. We understand many authors have granted exclusive audiobook rights (often to Audible). We are not seeking audiobook rights. Instead, we license serialized audio series adaptation rights, which are closer in nature to a TV dramatization, but in audio form, than to a traditional narrated audiobook. Rather than recording the manuscript verbatim, we create a scripted, episodic adaptation featuring dual-cast or full-cast performances, cinematic sound design, and structured cliffhanger arcs. Episodes run ~10 minutes and are released serially, with progression-based monetization. This format functions as an incremental revenue stream alongside print, ebook, KU, and audiobook sales, not in competition with them. Given the layered world-building and sustained narrative momentum in A Scoring Chance Series, we see strong alignment with this dramatized serialized format. Pocket FM is the world's largest dedicated audio series platform, trusted by leading publishers and IP holders including Naver, Kakao, Blackstone, Recorded Books, Aethon, and China Literature. Our catalog includes globally recognized titles such as Solo Leveling, The Primal Hunter, and Omniscient Reader's Viewpoint. In the past 12 months, we've delivered: 120 billion minutes of listening 18 million monthly active users $342M in revenue 200+ million global downloads Our app is rated 4.7 on the App Store and 4.5 on Google Play. Several titles have scaled meaningfully through this model, including: My Vampire System: 1B+ listens, $100M+ revenue Saving Nora: $42M revenue The Duke's Masked Bride: 641M plays The Alpha's Bride: 415M plays You can hear an example of our production quality here: https://pocketfm.com/show/ba2d9038fc3853c464c8be7a34a0576f26145106 We are proposing: License Fee: Revenue Share Only Revenue Share: 12% of Revenue Exclusive serialized audio series adaptation rights (distinct from audiobook rights) English language (U.S./U.K.) 5-10 year term Full IP ownership retained by the author We are focused on long-term partnerships and would welcome discussion around additional titles within your catalog as well. If of interest, I'd be glad to schedule a brief call to discuss further. Best regards, Pulaksh Khimesara US Licensing & Commissioning Pocket FM | AU78: Not Found
